{
  "mood": "السوق في حالة تفاؤل حذر مدفوعاً بآمال السلام بين أمريكا وإيران وتوقعات نمو الذكاء الاصطناعي",
  "moves": [
    {
      "sym": "SE",
      "price": "$103.30",
      "change": "+13.9%",
      "rsi": "",
      "why": "أداء قوي نسبياً لشركة Sea Limited في ظل تحسن مزاج المستثمرين تجاه أسهم التكنولوجيا الآسيوية"
    },
    {
      "sym": "BABA",
      "price": "$96.14",
      "change": "-13.9%",
      "rsi": "",
      "why": "ضغوط مستمرة على السهم رغم تحسن المزاج العام، والمحفظة لا تزال في خسارة"
    },
    {
      "sym": "ADBE",
      "price": "$219.72",
      "change": "-14.7%",
      "rsi": "",
      "why": "تراجع ملحوظ منذ سعر الشراء، والسهم يعاني ضغطاً في قطاع برمجيات الذكاء الاصطناعي"
    },
    {
      "sym": "TTD",
      "price": "$19.10",
      "change": "-17.4%",
      "rsi": "",
      "why": "The Trade Desk يتراجع بشكل لافت، ومزاج المستثمرين تجاه الإعلانات الرقمية يبقى متحفظاً"
    },
    {
      "sym": "GRAB",
      "price": "$3.90",
      "change": "+5.7%",
      "rsi": "",
      "why": "أداء إيجابي متواضع لشركة Grab في سياق تعافي أسهم التكنولوجيا الآسيوية"
    },
    {
      "sym": "SHOP",
      "price": "$119.46",
      "change": "+5.6%",
      "rsi": "",
      "why": "Shopify يحافظ على زخم إيجابي خفيف مدعوماً بتوقعات التجارة الإلكترونية"
    },
    {
      "sym": "CRM",
      "price": "$166.11",
      "change": "-18.7%",
      "rsi": "",
      "why": "Salesforce تحت ضغط كبير منذ الشراء رغم قصة الذكاء الاصطناعي الإيجابية على المدى البعيد"
    },
    {
      "sym": "NICE",
      "price": "$96.74",
      "change": "+5.2%",
      "rsi": "",
      "why": "أداء إيجابي معتدل لشركة NICE في قطاع برمجيات المؤسسات"
    },
    {
      "sym": "TMDX",
      "price": "$68.86",
      "change": "+2.8%",
      "rsi": "",
      "why": "TransMedics يسجل مكسباً طفيفاً في قطاع التكنولوجيا الطبية"
    },
    {
      "sym": "SMCI",
      "price": "$27.22",
      "change": "-6.1%",
      "rsi": "",
      "why": "Super Micro Computer يتراجع رغم الطلب المتزايد على خوادم الذكاء الاصطناعي"
    },
    {
      "sym": "BMRN",
      "price": "$58.99",
      "change": "+6.7%",
      "rsi": "",
      "why": "BioMarin تسجل مكسباً إيجابياً في قطاع الأدوية النادرة"
    },
    {
      "sym": "NVO",
      "price": "$50.43",
      "change": "+14.1%",
      "rsi": "",
      "why": "Novo Nordisk يحقق أداءً قوياً مدعوماً باستمرار الطلب على أدوية السمنة والسكري"
    },
    {
      "sym": "ELF",
      "price": "$76.42",
      "change": "+32.7%",
      "rsi": "",
      "why": "e.l.f. Beauty يمثل أفضل أداء في المحفظة بمكسب يتجاوز 32% منذ الشراء"
    },
    {
      "sym": "CPRT",
      "price": "$30.01",
      "change": "+0.0%",
      "rsi": "",
      "why": "Copart يراوح مكانه تقريباً دون تغيير يذكر منذ الشراء"
    }
  ],
  "news": [
    {
      "title": "تفاؤل السوق بآمال السلام بين أمريكا وإيران يدعم أسهم التكنولوجيا",
      "syms": ["SE", "BABA", "GRAB", "SHOP", "CRM", "ADBE", "TTD", "NICE", "SMCI", "TMDX"],
      "sentiment": "positive"
    },
    {
      "title": "تصريحات باليهاباتيا: الذكاء الاصطناعي قد يرفع الناتج المحلي الأمريكي 50% — دعم لقطاع التكنولوجيا",
      "syms": ["CRM", "ADBE", "TTD", "NICE", "SMCI", "SE", "SHOP"],
      "sentiment": "positive"
    },
    {
      "title": "أزمة طاقة الذكاء الاصطناعي تُبرز أهمية البنية التحتية لشركات التكنولوجيا",
      "syms": ["SMCI", "CRM", "ADBE"],
      "sentiment": "neutral"
    }
  ],
  "dates": []
}