{
  "market": "السوق الأمريكي شهد أداءً إيجابياً بقيادة قطاعات التقنية والتجزئة، حيث ارتفعت أسهم التكنولوجيا بشكل عام رغم تحذيرات من ذروة الرافعة المالية التي تجاوزت 1.5 تريليون دولار. قطاع الرقائق جاء متفاوتاً بعد نتائج TSMC التي فاقت التوقعات لكن السهم تراجع لأن السوق كان قد سعّر الخبر مسبقاً، مما يعكس مستويات تقييم مرتفعة في القطاع.",
  "narrative": "يوم لافت لمحفظة أحمد، والبطلة الكبرى اليوم بلا منازع هي ELF التي قفزت +8.09% في جلسة واحدة لتصل قيمتها إلى 3,859 دولار مع ربح منذ الشراء بلغ +38.3% — هذا النوع من الحركة اليومية يستحق البحث عن المحرك خلفه. في الجانب الآخر، BABA أضافت +4.67% اليوم وهي تُراكم ربحاً منذ الشراء بلغ +7.7%، بينما SE واصلت صعودها بـ+1.58% يومياً مع ربح منذ الشراء +16.5%. أما ADBE فتضغط على المحفظة بتراجع -1.06% اليوم فوق خسارتها المتراكمة منذ الشراء البالغة -8.9%، وكذلك NVO التي تراجعت -1.41% اليوم رغم أنها لا تزال في المنطقة الخضراء منذ الشراء بـ+12.2%. TTD تبقى الجرح الأعمق في المحفظة بخسارة -19.4% منذ الشراء، وإن استقرت اليوم عند +0.27%. التحذيرات الماكرو حول ذروة الرافعة المالية تستوجب المتابعة، لكنها لم تُترجم بعد إلى ضغط واضح على مراكز أحمد. القرار في النهاية عندك يا أحمد.",
  "moves": [
    {
      "sym": "ELF",
      "price": "79.65",
      "change": "+8.09%",
      "rsi": "",
      "why": "أقوى حركة يومية في المحفظة اليوم (منذ الشراء: +38.3%)"
    },
    {
      "sym": "BABA",
      "price": "120.34",
      "change": "+4.67%",
      "rsi": "",
      "why": "ارتفاع يومي ملحوظ يُعزز الربح منذ الشراء (منذ الشراء: +7.7%)"
    },
    {
      "sym": "SE",
      "price": "105.69",
      "change": "+1.58%",
      "rsi": "",
      "why": "تواصل الصعود التدريجي (منذ الشراء: +16.5%)"
    },
    {
      "sym": "CRM",
      "price": "173.79",
      "change": "+1.77%",
      "rsi": "53.9",
      "why": "ارتداد يومي إيجابي لكنه لا يزال في منطقة الخسارة (منذ الشراء: -15.0%)"
    },
    {
      "sym": "NVO",
      "price": "49.61",
      "change": "-1.41%",
      "rsi": "62.6",
      "why": "تراجع يومي طفيف مع RSI يقترب من منطقة التشبع الشرائي (منذ الشراء: +12.2%)"
    },
    {
      "sym": "ADBE",
      "price": "234.74",
      "change": "-1.06%",
      "rsi": "61.1",
      "why": "ضغط يومي إضافي على خسارة متراكمة (منذ الشراء: -8.9%)"
    },
    {
      "sym": "SMCI",
      "price": "23.83",
      "change": "-1.45%",
      "rsi": "",
      "why": "أصغر مركز في المحفظة يواصل التراجع (منذ الشراء: -17.8%)"
    },
    {
      "sym": "GRAB",
      "price": "3.62",
      "change": "+1.4%",
      "rsi": "",
      "why": "ارتداد يومي طفيف لكن المركز لا يزال في الخسارة الطفيفة (منذ الشراء: -1.9%)"
    },
    {
      "sym": "TTD",
      "price": "18.64",
      "change": "+0.27%",
      "rsi": "",
      "why": "استقرار يومي شبه كامل رغم الخسارة الكبيرة المتراكمة (منذ الشراء: -19.4%)"
    },
    {
      "sym": "TMDX",
      "price": "73.47",
      "change": "-0.69%",
      "rsi": "",
      "why": "تراجع يومي بسيط مع ربح متراكم جيد (منذ الشراء: +9.7%)"
    }
  ],
  "opportunity": {
    "sym": "MU",
    "why": "وفقاً لبيانات التقييم الكمي من قائمة متابعة Seeking Alpha (بتاريخ 2026-07-19)، حصل MU على تقييمات استثنائية: النمو A+ والربحية A+ والزخم A+ مع درجة كمية إجمالية 4.99 من 5، وجاء RSI عند 41 مما يشير إلى أن السهم لم يدخل بعد منطقة التشبع الشرائي رغم تقييماته القوية. السهم ينتمي لقطاع تقنية المعلومات وسعره الموثق في البيانات 848.95 دولار — المصدر حصراً قائمة المتابعة الخاصة ولا يمثل مسحاً لكامل السوق."
  },
  "risk_flags": [
    "تحذير ماكرو: ديون الهامش والرافعة المالية تبلغ ذروة تاريخية بـ1.5 تريليون دولار وفق تقارير Seeking Alpha — إشارة تحذيرية تسبق تاريخياً تصحيحات حادة",
    "NVO: RSI عند 62.6 يقترب من منطقة التشبع الشرائي",
    "ADBE: RSI عند 61.1 مع خسارة متراكمة -8.9% منذ الشراء",
    "TTD: خسارة متراكمة -19.4% منذ الشراء وهي الأعلى في المحفظة ضمن التكنولوجيا",
    "SMCI: أصغر مركز بالقيمة (80 دولار) مع خسارة -17.8% منذ الشراء",
    "موجة أرباح الشركات الكبرى قريبة — مايكروسوفت وألفابت أمام تساؤلات جوهرية حول نمو الذكاء الاصطناعي قد تؤثر على مزاج قطاع التقنية بشكل عام"
  ],
  "dates": [
    {
      "event": "نتائج مايكروسوفت للربع الثاني 2026 — محاور حاسمة: نمو Azure والذكاء الاصطناعي",
      "time": "قريباً — تاريخ محدد غير وارد في البيانات"
    },
    {
      "event": "نتائج ألفابت للربع الثاني 2026 — تحديات المنافسة من الذكاء الاصطناعي التوليدي",
      "time": "قريباً — تاريخ محدد غير وارد في البيانات"
    }
  ]
}