{
  "type": "weekly",
  "schema": 2,
  "date": "2026-07-06",
  "nickname": "rashed",
  "as_of": {
    "prices": "2026-07-06",
    "sa": "2026-07-01",
    "news": "2026-07-06"
  },
  "verdict": {
    "total_value": 621266,
    "holdings": 56,
    "tech_concentration_pct": 70.4,
    "review_count": 15,
    "watch_count": 10,
    "strong_count": 5,
    "stress_tech_minus20": 87496,
    "biggest_risk": "التركز التقني البالغ 70.4% يعني أن سيناريو انخفاض 20% في هذا القطاع سيُولّد خسارة محتملة تُقدَّر بـ87,496 دولار محسوبة مسبقاً، وهو ما يتقاطع مع تحذيرات السيولة والتحليل الفني الصادرة هذا الأسبوع."
  },
  "summary": "بناءً على أسعار 2026-07-06 وتقييمات SA بتاريخ 2026-07-01، تُظهر المحفظة تركزاً تقنياً مرتفعاً يبلغ 70.4% من إجمالي قيمة 621,266 دولار، مع وجود 15 سهماً تحت المراجعة و10 أسهم في قائمة المراقبة و5 أسهم بتصنيف قوي. شهد هذا الأسبوع تحركات يومية حادة في عدة أسهم كـIOT (+19.85%) وPLTR (+17.31%) وOKTA (+17.58%)، في حين تراجع MU وBTBT وVICR بأكثر من 11% في يوم واحد. يُضاف إلى ذلك تحذير من استنزاف سيولة بـ350 مليار دولار هذا الصيف وتحليل فني يُنبّه من نمط انعكاس محتمل على S&P 500، وهو ما يرفع من أهمية متابعة أسهم المحفظة ذات التقلب العالي في هذه المرحلة.",
  "stocks": [
    {
      "sym": "DUOL",
      "price": 130.765,
      "glPct": -48.4,
      "dayPct": 7.63,
      "value": 24885,
      "weight": 4,
      "quant": 1.57,
      "V": "C-",
      "G": "F",
      "P": "A",
      "M": "D-",
      "R": "C+",
      "rsi": 45.9,
      "earnDays": 30,
      "target": 114.4,
      "gapPct": -12.5,
      "sector": "tech",
      "verdict": "review",
      "reasons": [
        "quant<2",
        "momentum D/F on >$5K"
      ],
      "thesis": "يتداول السهم عند 130.765 دولار بخسارة تراكمية 48.4% وقيمة 24,885 دولار في المحفظة، وجاء تصنيفه الكمي عند 1.57 وهو دون العتبة المقبولة مما يُعضّد حكم المراجعة. التقييم المختلط بين نمو F وزخم D- يعكس ضعفاً هيكلياً رغم تقييم ربحية A، فيما يبقى السعر الحالي أعلى من هدف المحللين البالغ 114.4 دولار بفجوة سالبة 12.5%.",
      "watch": "كسر مستوى هدف المحللين 114.4 دولار أو نتائج الأرباح خلال 30 يوماً"
    },
    {
      "sym": "MSFT",
      "price": 386.61,
      "glPct": -4.8,
      "dayPct": 3.66,
      "value": 32658,
      "weight": 5.3,
      "quant": 3.46,
      "V": "D-",
      "G": "C",
      "P": "A+",
      "M": "D+",
      "R": "B-",
      "rsi": 41.3,
      "earnDays": null,
      "target": 550.28,
      "gapPct": 42.3,
      "sector": "tech",
      "verdict": "review",
      "reasons": [
        "momentum D/F on >$5K"
      ],
      "thesis": "يحمل السهم قيمة 32,658 دولار بخسارة تراكمية 4.8% وتصنيف قيمة D- مقابل ربحية A+، مما يعكس غلاء تقييمي وفق المعطيات المقدمة. ارتفع 3.66% خلال اليوم لكن الزخم D+ يُفسّر تصنيف المراجعة، في حين يُشير هدف المحللين 550.28 دولار إلى فجوة إيجابية 42.3% عن السعر الحالي.",
      "watch": "استعادة قوة الزخم أو الاقتراب من مناطق دعم الـ RSI عند 41.3"
    },
    {
      "sym": "AMZN",
      "price": 245.26,
      "glPct": 19.3,
      "dayPct": 5.4,
      "value": 37417,
      "weight": 6,
      "quant": 4.94,
      "V": "D+",
      "G": "A-",
      "P": "A+",
      "M": "B-",
      "R": "A-",
      "rsi": 44.9,
      "earnDays": 24,
      "target": 308.03,
      "gapPct": 25.6,
      "sector": "tech",
      "verdict": "strong",
      "reasons": [],
      "thesis": "السهم الأقوى في القطاع التقني بتصنيف كمي 4.94 وتقييم نمو A- وربحية A+، مع مكاسب تراكمية 19.3% وقيمة 37,417 دولار وهي الأعلى في القائمة المختارة. هدف المحللين عند 308.03 دولار يتضمن فجوة إيجابية 25.6% عن السعر الحالي 245.26، والأرباح مرتقبة خلال 24 يوماً مما يجعله حدثاً للمراقبة.",
      "watch": "نتائج الأرباح المرتقبة خلال 24 يوماً"
    },
    {
      "sym": "ATYR",
      "price": 0.6241,
      "glPct": -72.5,
      "dayPct": 18.2,
      "value": 8426,
      "weight": 1.4,
      "quant": 1.48,
      "V": "B+",
      "G": "B",
      "P": "C-",
      "M": "D",
      "R": "B",
      "rsi": 57.9,
      "earnDays": 31,
      "target": 5.13,
      "gapPct": 722,
      "sector": "bio",
      "verdict": "review",
      "reasons": [
        "loss>=50%",
        "quant<2",
        "momentum D/F on >$5K",
        "day move >=8%"
      ],
      "thesis": "تراجع السهم 72.5% تراكمياً ليصل إلى 0.6241 دولار مع قفزة يومية 18.2% وهو ما يستوجب الانتباه، فيما التصنيف الكمي 1.48 وتقييم ربحية C- يُضعفان الثقة في الاستمرارية. هدف المحللين عند 5.13 دولار يبدو بعيداً جداً عن السعر الحالي بفجوة 722% مما يعكس توقعات مضاربية لا أساسية.",
      "watch": "استمرار التحرك اليومي الحاد واقتراب نتائج الأرباح خلال 31 يوماً"
    },
    {
      "sym": "MVST",
      "price": 1.175,
      "glPct": -74.3,
      "dayPct": 5.86,
      "value": 7159,
      "weight": 1.2,
      "quant": 2.94,
      "V": "A",
      "G": "B",
      "P": "C-",
      "M": "F",
      "R": "A-",
      "rsi": 41.1,
      "earnDays": 34,
      "target": 4.8,
      "gapPct": 308.5,
      "sector": "industrials",
      "verdict": "review",
      "reasons": [
        "loss>=50%",
        "momentum D/F on >$5K"
      ],
      "thesis": "خسر السهم 74.3% تراكمياً ويتداول عند 1.175 دولار بقيمة 7,159 دولار، ورغم تقييم القيمة A والنمو B فإن الزخم F يُعدّ العائق الرئيسي للتصنيف الإيجابي. هدف المحللين عند 4.8 دولار يعني فجوة 308.5% لكن ضعف الزخم يحول دون الاستناد لهذا الهدف في المدى القريب.",
      "watch": "تحسن مؤشرات الزخم أو نتائج الأرباح خلال 34 يوماً"
    },
    {
      "sym": "CRM",
      "price": 166.585,
      "glPct": -30.4,
      "dayPct": 5.19,
      "value": 16659,
      "weight": 2.7,
      "quant": 3.38,
      "V": "C",
      "G": "D+",
      "P": "A+",
      "M": "D",
      "R": "B",
      "rsi": 39.9,
      "earnDays": 50,
      "target": 265.75,
      "gapPct": 59.5,
      "sector": "tech",
      "verdict": "review",
      "reasons": [
        "momentum D/F on >$5K"
      ],
      "thesis": "يتداول السهم عند 166.585 دولار بخسارة تراكمية 30.4% وتصنيف نمو D+ مقابل ربحية A+، وهدف المحللين 265.75 دولار يُشير إلى فجوة إيجابية 59.5% تعكس توقعات انتعاش محتملة. الزخم D يُبقيه تحت المراجعة، وموعد الأرباح بعد 50 يوماً يُعطي وقتاً لمراقبة تطور الزخم.",
      "watch": "تحسن الزخم فوق تصنيف C أو كسر مستويات فنية محورية قبل نتائج الأرباح"
    },
    {
      "sym": "BTBT",
      "price": 1.74,
      "glPct": -56.8,
      "dayPct": -12.56,
      "value": 8700,
      "weight": 1.4,
      "quant": 2.94,
      "V": "A-",
      "G": "B-",
      "P": "D",
      "M": "C",
      "R": "-",
      "rsi": 45.2,
      "earnDays": null,
      "target": 6,
      "gapPct": 244.8,
      "sector": "spec",
      "verdict": "review",
      "reasons": [
        "loss>=50%",
        "day move >=8%"
      ],
      "thesis": "تراجع السهم 56.8% تراكمياً وسجّل انخفاضاً يومياً حاداً 12.56% عند سعر 1.74 دولار، وتصنيف الربحية D يُضاف إلى عدم توفر تغطية محللين لهذا السهم. ينتمي لقطاع المضاربة وقد يتأثر بالأخبار السلبية المتعلقة بقطاع العملات المشفرة المُشار إليها هذا الأسبوع.",
      "watch": "التراجع اليومي الحاد وتداعيات أخبار قطاع العملات المشفرة"
    },
    {
      "sym": "PONY",
      "price": 6.965,
      "glPct": -65.3,
      "dayPct": 1.38,
      "value": 6968,
      "weight": 1.1,
      "quant": 1.15,
      "V": "B",
      "G": "B-",
      "P": "F",
      "M": "F",
      "R": "D+",
      "rsi": 31.8,
      "earnDays": 49,
      "target": 27,
      "gapPct": 287.7,
      "sector": "tech",
      "verdict": "review",
      "reasons": [
        "loss>=50%",
        "quant<2",
        "momentum D/F on >$5K"
      ],
      "thesis": "يحمل السهم خسارة تراكمية 65.3% ويتداول عند 6.965 دولار بتصنيف كمي 1.15 وهو الأدنى في القائمة، مع تقييم ربحية F وزخم F مما يجعله من أضعف الأسهم في المحفظة. هدف المحللين عند 27 دولار يعني فجوة 287.7% لكن الـ RSI عند 31.8 يعكس ضغطاً بيعياً مستمراً.",
      "watch": "الـ RSI عند 31.8 قرب حدود التشبع البيعي ونتائج الأرباح خلال 49 يوماً"
    },
    {
      "sym": "NTLA",
      "price": 17.83,
      "glPct": -3.2,
      "dayPct": 6.89,
      "value": 19371,
      "weight": 3.1,
      "quant": 4.34,
      "V": "C-",
      "G": "B-",
      "P": "C",
      "M": "B+",
      "R": "A-",
      "rsi": 66.4,
      "earnDays": 37,
      "target": 26.13,
      "gapPct": 46.6,
      "sector": "bio",
      "verdict": "strong",
      "reasons": [],
      "thesis": "يُعدّ من أسهم المحفظة البيوتكنولوجية القوية بتصنيف كمي 4.34 وزخم B+ وتصنيف R بـA-، مع خسارة تراكمية طفيفة 3.2% فقط وقيمة 19,371 دولار. هدف المحللين عند 26.13 دولار يُتيح فجوة إيجابية 46.6% عن السعر الحالي 17.83، والأرباح مرتقبة خلال 37 يوماً.",
      "watch": "نتائج الأرباح خلال 37 يوماً وكسر مستوى الـ RSI 66.4 نحو الأعلى"
    },
    {
      "sym": "QQQ",
      "price": 723.26,
      "glPct": 63.8,
      "dayPct": 2.37,
      "value": 18588,
      "weight": 3,
      "quant": 4.33,
      "V": "-",
      "G": "-",
      "P": "-",
      "M": "-",
      "R": "-",
      "rsi": 56.6,
      "earnDays": null,
      "target": null,
      "gapPct": null,
      "sector": "etf",
      "verdict": "strong",
      "reasons": [],
      "thesis": "صندوق المؤشر يحقق مكاسب تراكمية 63.8% بقيمة 18,588 دولار وتصنيف كمي 4.33، وهو يُجسّد التعرض العام للأسهم التقنية في المحفظة. في ظل التحذيرات الفنية المتعلقة بـS&P 500 وضغوط السيولة المذكورة هذا الأسبوع، يكتسب متابعة حركة هذا الصندوق أهمية خاصة.",
      "watch": "مستويات الـ RSI عند 56.6 وتطور الوضع الفني لمؤشرات النمو"
    },
    {
      "sym": "SPY",
      "price": 751.37,
      "glPct": 44.2,
      "dayPct": 3.07,
      "value": 15779,
      "weight": 2.5,
      "quant": 4.08,
      "V": "-",
      "G": "-",
      "P": "-",
      "M": "-",
      "R": "-",
      "rsi": 55,
      "earnDays": null,
      "target": null,
      "gapPct": null,
      "sector": "etf",
      "verdict": "strong",
      "reasons": [],
      "thesis": "يُحقق الصندوق مكاسب تراكمية 44.2% بقيمة 15,779 دولار وتصنيف كمي 4.08، وهو أداة التوزيع الواسع في المحفظة. التحليل الفني المُشار إليه هذا الأسبوع حول نمط علم الثور على S&P 500 يجعل متابعة هذا الصندوق تحديداً أمراً جوهرياً.",
      "watch": "تطور نمط علم الثور المُشار إليه في التحليلات الفنية لهذا الأسبوع"
    },
    {
      "sym": "SERV",
      "price": 6.435,
      "glPct": -56.7,
      "dayPct": 7.07,
      "value": 4505,
      "weight": 0.7,
      "quant": 1.78,
      "V": "C+",
      "G": "A",
      "P": "F",
      "M": "D-",
      "R": "B-",
      "rsi": 41.1,
      "earnDays": 30,
      "target": null,
      "gapPct": null,
      "sector": "tech",
      "verdict": "review",
      "reasons": [
        "loss>=50%",
        "quant<2"
      ],
      "thesis": "يتداول السهم عند 6.435 دولار بخسارة تراكمية 56.7% وقيمة منخفضة 4,505 دولار، مع تصنيف كمي 1.78 دون العتبة وتقييم نمو A مقابل ربحية F. هدف المحللين غير متوفر مما يُقيّد تقييم الفجوة السعرية، والأرباح مرتقبة خلال 30 يوماً.",
      "watch": "نتائج الأرباح خلال 30 يوماً وتحسن التصنيف الكمي"
    },
    {
      "sym": "TEAM",
      "price": 85.355,
      "glPct": 8.4,
      "dayPct": 8.4,
      "value": 11051,
      "weight": 1.8,
      "quant": 3.21,
      "V": "B-",
      "G": "B-",
      "P": "B+",
      "M": "D",
      "R": "A",
      "rsi": 40,
      "earnDays": 30,
      "target": 136.79,
      "gapPct": 60.3,
      "sector": "tech",
      "verdict": "review",
      "reasons": [
        "momentum D/F on >$5K",
        "day move >=8%"
      ],
      "thesis": "ارتفع السهم 8.4% في يوم واحد ليصل إلى 85.355 دولار مع مكاسب تراكمية 8.4%، غير أن تصنيف الزخم D يُبقيه تحت المراجعة رغم تقييمات النمو والربحية المعقولة. هدف المحللين 136.79 دولار يُشير إلى فجوة إيجابية 60.3% والأرباح مرتقبة خلال 30 يوماً.",
      "watch": "استمرار حركة اليوم الحاد وتأثير نتائج الأرباح خلال 30 يوماً على الزخم"
    },
    {
      "sym": "PATH",
      "price": 12.085,
      "glPct": -18.4,
      "dayPct": 14.77,
      "value": 7823,
      "weight": 1.3,
      "quant": 3.07,
      "V": "B+",
      "G": "B-",
      "P": "A-",
      "M": "D+",
      "R": "C+",
      "rsi": 52.8,
      "earnDays": 57,
      "target": 14,
      "gapPct": 15.8,
      "sector": "tech",
      "verdict": "review",
      "reasons": [
        "momentum D/F on >$5K",
        "day move >=8%"
      ],
      "thesis": "قفز السهم 14.77% في يوم واحد ليصل إلى 12.085 دولار رغم خسارة تراكمية 18.4%، وتصنيف الزخم D+ لا يزال يُشكّل عائقاً رئيسياً للتصنيف القوي. هدف المحللين عند 14 دولار يُتيح فجوة معتدلة 15.8% والأرباح مرتقبة بعد 57 يوماً.",
      "watch": "ديمومة الارتفاع اليومي الحاد وتطور تصنيف الزخم"
    },
    {
      "sym": "ONTO",
      "price": 302.71,
      "glPct": 68.6,
      "dayPct": -6.55,
      "value": 15435,
      "weight": 2.5,
      "quant": 4.94,
      "V": "D+",
      "G": "B+",
      "P": "B",
      "M": "A",
      "R": "A",
      "rsi": 66.9,
      "earnDays": 30,
      "target": 365.75,
      "gapPct": 20.8,
      "sector": "tech",
      "verdict": "strong",
      "reasons": [],
      "thesis": "يُحقق السهم مكاسب تراكمية 68.6% وتصنيف كمي 4.94 مع زخم A وتصنيف R بـA، مما يجعله من أقوى الأسهم في المحفظة رغم تراجعه 6.55% اليوم. هدف المحللين 365.75 دولار يُتيح فجوة 20.8% والأرباح مرتقبة خلال 30 يوماً.",
      "watch": "نتائج الأرباح خلال 30 يوماً والتراجع اليومي 6.55%"
    },
    {
      "sym": "VISN",
      "price": 12.39,
      "glPct": -22.9,
      "dayPct": -1.51,
      "value": 6203,
      "weight": 1,
      "quant": 3.43,
      "V": "A+",
      "G": "D-",
      "P": "A+",
      "M": "D+",
      "R": "B+",
      "rsi": 51.5,
      "earnDays": 30,
      "target": 17,
      "gapPct": 37.2,
      "sector": "tech",
      "verdict": "review",
      "reasons": [
        "momentum D/F on >$5K"
      ],
      "thesis": "يتداول عند 12.39 دولار بخسارة تراكمية 22.9% مع تصنيف قيمة A+ يُعدّ الأعلى في قائمة التقييمات، غير أن تصنيف النمو D- يحول دون الارتقاء للتصنيف القوي. هدف المحللين 17 دولار يُشير إلى فجوة 37.2% والأرباح مرتقبة خلال 30 يوماً.",
      "watch": "نتائج الأرباح خلال 30 يوماً وتحسن تصنيف النمو"
    },
    {
      "sym": "SMMT",
      "price": 15.56,
      "glPct": -16.4,
      "dayPct": 11.06,
      "value": 6227,
      "weight": 1,
      "quant": 2.92,
      "V": "F",
      "G": "B-",
      "P": "F",
      "M": "D",
      "R": "A+",
      "rsi": 45.6,
      "earnDays": 28,
      "target": null,
      "gapPct": null,
      "sector": "bio",
      "verdict": "review",
      "reasons": [
        "momentum D/F on >$5K",
        "day move >=8%"
      ],
      "thesis": "ارتفع السهم 11.06% في يوم واحد ليصل إلى 15.56 دولار مع خسارة تراكمية 16.4%، لكن تصنيفي القيمة والربحية F يُنبّهان إلى ضعف أساسي رغم تصنيف R المتميز A+. هدف المحللين غير متوفر، والأرباح مرتقبة خلال 28 يوماً.",
      "watch": "نتائج الأرباح خلال 28 يوماً مع الزخم D الحالي"
    },
    {
      "sym": "ADBE",
      "price": 218.355,
      "glPct": -59.2,
      "dayPct": 7.71,
      "value": 2162,
      "weight": 0.3,
      "quant": 3.34,
      "V": "B+",
      "G": "D",
      "P": "A+",
      "M": "D-",
      "R": "A",
      "rsi": 39.3,
      "earnDays": 65,
      "target": null,
      "gapPct": null,
      "sector": "tech",
      "verdict": "review",
      "reasons": [
        "loss>=50%"
      ],
      "thesis": "يتداول السهم عند 218.355 دولار بخسارة تراكمية 59.2% وقيمة منخفضة جداً 2,162 دولار في المحفظة، وتصنيف النمو D مقابل ربحية A+ يعكس تبايناً واضحاً. هدف المحللين غير متوفر، والأرباح مرتقبة بعد 65 يوماً.",
      "watch": "الـ RSI عند 39.3 قرب مناطق التشبع البيعي"
    },
    {
      "sym": "PLTR",
      "price": 132.475,
      "glPct": 465.9,
      "dayPct": 17.31,
      "value": 11895,
      "weight": 1.9,
      "quant": 3.4,
      "V": "D+",
      "G": "A",
      "P": "A+",
      "M": "D",
      "R": "B+",
      "rsi": 38.9,
      "earnDays": 27,
      "target": null,
      "gapPct": null,
      "sector": "tech",
      "verdict": "review",
      "reasons": [
        "momentum D/F on >$5K",
        "day move >=8%"
      ],
      "thesis": "يُحقق السهم مكاسب تراكمية استثنائية 465.9% ويرتفع 17.31% في يوم واحد ليصل إلى 132.475 دولار، غير أن تصنيف الزخم D وتقييم القيمة D+ يُشيران إلى مخاوف تقييمية بعد هذه المكاسب الضخمة. هدف المحللين غير متوفر، والأرباح مرتقبة خلال 27 يوماً.",
      "watch": "نتائج الأرباح خلال 27 يوماً والـ RSI عند 38.9 رغم الارتفاع الحاد اليومي"
    },
    {
      "sym": "IBIT",
      "price": 36.08,
      "glPct": 1.8,
      "dayPct": 6.59,
      "value": 2037,
      "weight": 0.3,
      "quant": 1.11,
      "V": "-",
      "G": "-",
      "P": "-",
      "M": "-",
      "R": "-",
      "rsi": 32.3,
      "earnDays": null,
      "target": null,
      "gapPct": null,
      "sector": "spec",
      "verdict": "review",
      "reasons": [
        "quant<2"
      ],
      "thesis": "يتداول عند 36.08 دولار بمكاسب تراكمية طفيفة 1.8% وتصنيف كمي 1.11 وهو الأدنى في القائمة، وينتمي لقطاع المضاربة وقد يتأثر بالأخبار السلبية المتعلقة بقطاع العملات المشفرة الصادرة هذا الأسبوع. الـ RSI عند 32.3 يُقترب من مناطق التشبع البيعي.",
      "watch": "تطور أخبار قطاع العملات المشفرة والـ RSI عند 32.3"
    },
    {
      "sym": "MU",
      "price": 989.36,
      "glPct": 472.6,
      "dayPct": -12.63,
      "value": 39574,
      "weight": 6.4,
      "quant": 4.99,
      "V": "B+",
      "G": "A+",
      "P": "A+",
      "M": "A+",
      "R": "A",
      "rsi": 60,
      "earnDays": 85,
      "target": null,
      "gapPct": null,
      "sector": "tech",
      "verdict": "watch",
      "reasons": [
        "day move >=8%"
      ],
      "thesis": "يُحقق السهم مكاسب تراكمية استثنائية 472.6% بقيمة 39,574 دولار وهي الأعلى في المحفظة، مع تصنيف كمي 4.99 تقريباً مثالي وجميع تقييماته A وA+. التراجع اليومي الحاد 12.63% يُعدّ الحدث الرئيسي للمراقبة لهذا الأسبوع، والأرباح مرتقبة خلال 85 يوماً.",
      "watch": "أسباب التراجع اليومي الحاد 12.63% وتطور مؤشرات الذكاء الاصطناعي وأشباه الموصلات"
    },
    {
      "sym": "OKTA",
      "price": 146.125,
      "glPct": 59.1,
      "dayPct": 17.58,
      "value": 25367,
      "weight": 4.1,
      "quant": 4.85,
      "V": "C-",
      "G": "C+",
      "P": "A-",
      "M": "B+",
      "R": "B",
      "rsi": 72.2,
      "earnDays": 50,
      "target": 121.11,
      "gapPct": -17.1,
      "sector": "tech",
      "verdict": "watch",
      "reasons": [
        "day move >=8%",
        "RSI>70"
      ],
      "thesis": "قفز السهم 17.58% في يوم واحد ليصل إلى 146.125 دولار مع مكاسب تراكمية 59.1%، لكن الـ RSI عند 72.2 يُشير إلى مناطق التشبع الشرائي مما يُفسّر تصنيف المراقبة. هدف المحللين 121.11 دولار يقع أدنى من السعر الحالي بفجوة سالبة 17.1%، والأرباح مرتقبة خلال 50 يوماً.",
      "watch": "الـ RSI فوق 70 وهدف المحللين أدنى من السعر الحالي بـ17.1%"
    },
    {
      "sym": "GOOGL",
      "price": 364.78,
      "glPct": 40,
      "dayPct": 8.12,
      "value": 18370,
      "weight": 3,
      "quant": 3.49,
      "V": "F",
      "G": "B+",
      "P": "A+",
      "M": "A",
      "R": "A",
      "rsi": 47.9,
      "earnDays": 21,
      "target": 416.13,
      "gapPct": 14.1,
      "sector": "tech",
      "verdict": "watch",
      "reasons": [
        "day move >=8%"
      ],
      "thesis": "ارتفع السهم 8.12% في يوم واحد ليصل إلى 364.78 دولار مع مكاسب تراكمية 40%، لكن تقييم القيمة F يُشير إلى تساؤلات حول مستوى التقييم رغم تصنيفات الربحية والزخم المتميزة. هدف المحللين 416.13 دولار يُتيح فجوة 14.1% والأرباح مرتقبة خلال 21 يوماً.",
      "watch": "نتائج الأرباح المرتقبة خلال 21 يوماً وانعكاس تأثير أخبار أسهم الذكاء الاصطناعي الإيجابية"
    },
    {
      "sym": "VICR",
      "price": 290.265,
      "glPct": -13.8,
      "dayPct": -11.21,
      "value": 17234,
      "weight": 2.8,
      "quant": 4.98,
      "V": "D",
      "G": "A+",
      "P": "B-",
      "M": "A+",
      "R": "A",
      "rsi": 65.5,
      "earnDays": 14,
      "target": 387.5,
      "gapPct": 33.5,
      "sector": "tech",
      "verdict": "watch",
      "reasons": [
        "day move >=8%",
        "earnings<=14d"
      ],
      "thesis": "تراجع السهم 11.21% في يوم واحد ليصل إلى 290.265 دولار مع خسارة تراكمية 13.8%، والأرباح مرتقبة خلال 14 يوماً فقط مما يجعله الأقرب لحدث أرباح في القائمة. هدف المحللين 387.5 دولار يُتيح فجوة 33.5% والتصنيف الكمي 4.98 يُعدّ من الأعلى في المجموعة.",
      "watch": "نتائج الأرباح خلال 14 يوماً وهي الأقرب زمنياً في القائمة بأكملها"
    },
    {
      "sym": "APH",
      "price": 166.64,
      "glPct": 33.3,
      "dayPct": 1.78,
      "value": 16756,
      "weight": 2.7,
      "quant": 3.45,
      "V": "F",
      "G": "B+",
      "P": "A",
      "M": "B",
      "R": "B",
      "rsi": 71.3,
      "earnDays": 22,
      "target": 182.89,
      "gapPct": 9.8,
      "sector": "tech",
      "verdict": "watch",
      "reasons": [
        "RSI>70"
      ],
      "thesis": "يُحقق السهم مكاسب تراكمية 33.3% بقيمة 16,756 دولار، لكن الـ RSI عند 71.3 يُدخله منطقة التشبع الشرائي مما يُفسّر تصنيف المراقبة. هدف المحللين 182.89 دولار يُتيح فجوة معتدلة 9.8% والأرباح مرتقبة خلال 22 يوماً.",
      "watch": "الـ RSI فوق 70 ونتائج الأرباح خلال 22 يوماً"
    },
    {
      "sym": "PANW",
      "price": 354.24,
      "glPct": 100.9,
      "dayPct": 16.45,
      "value": 15055,
      "weight": 2.4,
      "quant": 3.47,
      "V": "D-",
      "G": "D+",
      "P": "A",
      "M": "A-",
      "R": "B-",
      "rsi": 79.4,
      "earnDays": 41,
      "target": null,
      "gapPct": null,
      "sector": "tech",
      "verdict": "watch",
      "reasons": [
        "day move >=8%",
        "RSI>70"
      ],
      "thesis": "يُحقق السهم مكاسب تراكمية 100.9% وارتفع 16.45% في يوم واحد ليصل إلى 354.24 دولار، لكن الـ RSI عند 79.4 يُعدّ الأعلى في القائمة ويُشير لمنطقة تشبع شرائي حادة. تقييم القيمة D- والنمو D+ يُشيران إلى تساؤلات أساسية عند هذا المستوى السعري.",
      "watch": "الـ RSI عند 79.4 وهو الأعلى في القائمة المختارة"
    },
    {
      "sym": "CRDO",
      "price": 264.4,
      "glPct": 102.7,
      "dayPct": 11.09,
      "value": 14362,
      "weight": 2.3,
      "quant": 4.97,
      "V": "C",
      "G": "A+",
      "P": "A",
      "M": "A",
      "R": "A+",
      "rsi": 58.4,
      "earnDays": 56,
      "target": null,
      "gapPct": null,
      "sector": "tech",
      "verdict": "watch",
      "reasons": [
        "day move >=8%"
      ],
      "thesis": "يُحقق السهم مكاسب تراكمية 102.7% وارتفع 11.09% في يوم واحد بتصنيف كمي 4.97 وجميع تقييماته عالية، مما يجعله من أقوى الأسهم في قطاع التقنية بالمحفظة. هدف المحللين غير متوفر، والأرباح مرتقبة خلال 56 يوماً.",
      "watch": "استمرار حركة الزخم القوية وتطور أخبار قطاع الذكاء الاصطناعي وأشباه الموصلات"
    },
    {
      "sym": "IOT",
      "price": 37.32,
      "glPct": 0.5,
      "dayPct": 19.85,
      "value": 14059,
      "weight": 2.3,
      "quant": 4.06,
      "V": "D",
      "G": "A-",
      "P": "B-",
      "M": "C-",
      "R": "B",
      "rsi": 51.9,
      "earnDays": 58,
      "target": 40.33,
      "gapPct": 8.1,
      "sector": "tech",
      "verdict": "watch",
      "reasons": [
        "day move >=8%"
      ],
      "thesis": "ارتفع السهم 19.85% في يوم واحد وهو الأعلى في القائمة اليومية ليصل إلى 37.32 دولار مع مكاسب تراكمية طفيفة 0.5%، وتصنيف الزخم C- يُبقيه في مراقبة الحذر رغم النمو A-. هدف المحللين 40.33 دولار يُتيح فجوة 8.1% والأرباح مرتقبة خلال 58 يوماً.",
      "watch": "أسباب الارتفاع اليومي الحاد 19.85% وديمومة هذه الحركة"
    },
    {
      "sym": "TTE",
      "price": 76.44,
      "glPct": -2.9,
      "dayPct": -0.43,
      "value": 9831,
      "weight": 1.6,
      "quant": 4.9,
      "V": "B+",
      "G": "C+",
      "P": "A+",
      "M": "C+",
      "R": "A-",
      "rsi": 24.7,
      "earnDays": 16,
      "target": 75.67,
      "gapPct": -1,
      "sector": "energy",
      "verdict": "watch",
      "reasons": [
        "RSI<30"
      ],
      "thesis": "يتداول السهم عند 76.44 دولار بخسارة تراكمية طفيفة 2.9% مع الـ RSI عند 24.7 وهو الأدنى في القائمة ويُشير بوضوح لمنطقة التشبع البيعي، وهو الوحيد في قطاع الطاقة مما يُعطيه دوراً تنويعياً في المحفظة. هدف المحللين 75.67 دولار أدنى قليلاً من السعر الحالي بفجوة سالبة 1%، والأرباح مرتقبة خلال 16 يوماً.",
      "watch": "الـ RSI عند 24.7 وهو الأدنى في القائمة ونتائج الأرباح خلال 16 يوماً"
    },
    {
      "sym": "SEZL",
      "price": 175.85,
      "glPct": 93.8,
      "dayPct": 3.1,
      "value": 7579,
      "weight": 1.2,
      "quant": 4.96,
      "V": "A-",
      "G": "A+",
      "P": "A",
      "M": "A+",
      "R": "A+",
      "rsi": 76.7,
      "earnDays": 29,
      "target": null,
      "gapPct": null,
      "sector": "tech",
      "verdict": "watch",
      "reasons": [
        "RSI>70"
      ],
      "thesis": "يُحقق السهم مكاسب تراكمية 93.8% بتصنيف كمي 4.96 وجميع تقييماته عالية A وA+، غير أن الـ RSI عند 76.7 يُدخله منطقة التشبع الشرائي مما يُفسّر تصنيف المراقبة. هدف المحللين غير متوفر، والأرباح مرتقبة خلال 29 يوماً.",
      "watch": "الـ RSI عند 76.7 ونتائج الأرباح خلال 29 يوماً"
    }
  ],
  "clusters": [
    {
      "name": "أسهم التقنية ذات الزخم العالي مع RSI مرتفع",
      "syms": [
        "PANW",
        "OKTA",
        "SEZL",
        "APH"
      ],
      "note": "تشترك هذه الأسهم في RSI يتجاوز 70 وتحقيق مكاسب تراكمية إيجابية مع تحركات يومية حادة، مما يضعها في منطقة التشبع الشرائي بحسب المعطيات المقدمة",
      "value": 64757
    },
    {
      "name": "أسهم التقنية بخسائر تراكمية كبيرة وزخم ضعيف",
      "syms": [
        "DUOL",
        "CRM",
        "PONY",
        "ADBE"
      ],
      "note": "تجمع هذه الأسهم خسائر تراكمية تتراوح بين 30% و59% مع تصنيفات زخم بين D- وD، مما يُقيّد إمكانية التعافي وفق التقييمات المقدمة",
      "value": 50674
    },
    {
      "name": "أسهم التقنية بمكاسب استثنائية وتقييمات كمية عالية",
      "syms": [
        "MU",
        "CRDO",
        "ONTO",
        "AMZN"
      ],
      "note": "تتشابه هذه الأسهم في التصنيف الكمي العالي فوق 4.9 مع مكاسب تراكمية قوية وتقييمات نمو وربحية متميزة وفق البيانات المقدمة",
      "value": 106788
    },
    {
      "name": "أسهم المضاربة عالية المخاطر",
      "syms": [
        "ATYR",
        "MVST",
        "BTBT",
        "IBIT"
      ],
      "note": "تتقاطع في خسائر تراكمية تتجاوز 56% وتصنيفات كمية منخفضة دون 3 مع تقلبات يومية حادة وانتماء لقطاعي المضاربة والبيوتك",
      "value": 26322
    },
    {
      "name": "صناديق المؤشرات كغطاء التنويع",
      "syms": [
        "QQQ",
        "SPY"
      ],
      "note": "كلاهما يُحقق مكاسب تراكمية إيجابية وتصنيف كمي فوق 4 ويعكسان الأداء العام للسوق، غير أن التحذيرات الفنية لهذا الأسبوع تجعل متابعتهما مزدوجة الأهمية",
      "value": 34367
    },
    {
      "name": "أسهم التقنية بتحركات يومية حادة هذا الأسبوع",
      "syms": [
        "PLTR",
        "IOT",
        "GOOGL",
        "CRDO",
        "TEAM",
        "PATH",
        "SMMT"
      ],
      "note": "ارتفعت جميعها بأكثر من 8% في يوم واحد مع تأثر مباشر بتدفق الشراء على أسهم الذكاء الاصطناعي والتقنية المُشار إليه في أخبار الأسبوع",
      "value": 83787
    }
  ],
  "hedge": "وجود TTE بقطاع الطاقة يُمثّل التنويع الوحيد الفعلي خارج التقنية والمضاربة في القائمة المختارة، فيما يُشير RSIه عند 24.7 لمنطقة تشبع بيعي قد تكون ذات دلالة في حال تصاعد ضغوط السيولة المُشار إليها هذا الأسبوع البالغة 350 مليار دولار.",
  "stress": [
    {
      "scenario": "تصحيح تقنية -20%",
      "impact_usd": -87496
    }
  ],
  "generated": "2026-07-06T18:32:52.836Z"
}