{"content":"```json\n{\n  \"mood\": \"السوق في حالة تفاؤل حذر مع آمال السلام بين أمريكا وإيران وزخم الذكاء الاصطناعي\",\n  \"moves\": [\n    {\n      \"sym\": \"SE\",\n      \"price\": \"$104.84\",\n      \"change\": \"+15.6%\",\n      \"rsi\": \"RSI 68.82\",\n      \"why\": \"زخم قوي قرب منطقة التشبع الشرائي، أرباح قادمة في 11 أغسطس، محللو JP Morgan وBarclays يحافظون على تقييم Overweight\"\n    },\n    {\n      \"sym\": \"ELF\",\n      \"price\": \"$77.30\",\n      \"change\": \"+34.2%\",\n      \"rsi\": \"RSI 74.45\",\n      \"why\": \"منطقة تشبع شرائي واضحة، السعر الحالي يتجاوز متوسط المحللين البالغ 74.78 دولار، Guggenheim يحافظ على Buy ومورغان ستانلي عند Equal Weight\"\n    },\n    {\n      \"sym\": \"BABA\",\n      \"price\": \"$97.20\",\n      \"change\": \"-13.0%\",\n      \"rsi\": \"RSI 24.85\",\n      \"why\": \"منطقة تشبع بيعي حاد، السعر بعيد جداً عن هدف المحللين 187 دولار، أرباح قادمة في 28 أغسطس، JP Morgan وBarclays يحافظان على Overweight\"\n    },\n    {\n      \"sym\": \"ADBE\",\n      \"price\": \"$217.70\",\n      \"change\": \"-15.5%\",\n      \"rsi\": \"RSI 48.78\",\n      \"why\": \"تراجع حاد مع تخفيضات متعددة في التوصيات مؤخراً، Stifel خفّض إلى Hold وEvercore إلى In Line وWilliam Blair إلى Market Perform، الهدف الإجماعي 260 دولار\"\n    },\n    {\n      \"sym\": \"CRM\",\n      \"price\": \"$165.09\",\n      \"change\": \"-19.2%\",\n      \"rsi\": \"RSI 49.03\",\n      \"why\": \"أكبر خسارة في القطاع، السعر أسفل SMA200 بكثير، Guggenheim رفع إلى Buy بتاريخ 1 يوليو، الهدف الإجماعي 265 دولار\"\n    },\n    {\n      \"sym\": \"TTD\",\n      \"price\": \"$19.16\",\n      \"change\": \"-17.1%\",\n      \"rsi\": \"RSI 47.37\",\n      \"why\": \"ضغط مستمر بعد تخفيضات Oppenheimer وKeybanc وWilliam Blair في مايو، أرباح الربع الأخير خيّبت توقعات بعض المحللين\"\n    },\n    {\n      \"sym\": \"NVO\",\n      \"price\": \"$50.48\",\n      \"change\": \"+14.2%\",\n      \"rsi\": \"RSI 73.31\",\n      \"why\": \"منطقة تشبع شرائي، Berenberg رفّع إلى Buy مؤخراً، لكن Goldman وJP Morgan خفّضا التوصية في مطلع 2026، الهدف الإجماعي عند 45 دولار فقط\"\n    },\n    {\n      \"sym\": \"SHOP\",\n      \"price\": \"$120.28\",\n      \"change\": \"+6.3%\",\n      \"rsi\": \"RSI 58.87\",\n      \"why\": \"أداء إيجابي، Truist رفّع إلى Buy في فبراير، Mizuho رفّع إلى Outperform، Wolfe خفّض إلى Peer Perform في يناير، الهدف الإجماعي 156 دولار\"\n    },\n    {\n      \"sym\": \"GRAB\",\n      \"price\": \"$3.87\",\n      \"change\": \"+4.9%\",\n      \"rsi\": \"RSI 67.16\",\n      \"why\": \"زخم إيجابي تدريجي، China Renaissance رفّع إلى Buy في مايو، JP Morgan رفّع إلى Overweight في فبراير، الهدف الإجماعي 6 دولار\"\n    },\n    {\n      \"sym\": \"BMRN\",\n      \"price\": \"$59.00\",\n      \"change\": \"+6.7%\",\n      \"rsi\": \"RSI 60.87\",\n      \"why\": \"أداء معتدل إيجابي، Canaccord رفّع إلى Buy في يناير 2026، الهدف الإجماعي 89 دولار يشير إلى إمكانية ارتفاع كبيرة\"\n    }\n  ],\n  \"news\": [\n    {\n      \"title\": \"الذكاء الاصطناعي يدفع النمو في قطاع التكنولوجيا وسط تفاؤل المستثمرين\",\n      \"syms\": [\"SE\", \"SHOP\", \"CRM\", \"ADBE\", \"TTD\"],\n      \"sentiment\": \"positive\"\n    },\n    {\n      \"title\": \"آمال السلام بين أمريكا وإيران تدعم أسهم التكنولوجيا والنمو\",\n      \"syms\": [\"SE\", \"GRAB\", \"BABA\"],\n      \"sentiment\": \"positive\"\n    }\n  ],\n  \"dates\": [\n    {\n      \"event\": \"أرباح SE - EPS متوقع 0.87 دولار\",\n      \"time\": \"11 أغسطس 2026\"\n    },\n    {\n      \"event\": \"أرباح NICE - EPS متوقع 2.63 دولار\",\n      \"time\": \"13 أغسطس 2026\"\n    },\n    {\n      \"event\": \"أرباح BABA - EPS متوقع 1.45 دولار\",\n      \"time\": \"28 أغسطس 2026\"\n    }\n  ]\n}\n```","nickname":"ahmed","date":"2026-07-02","savedAt":"2026-07-02T14:07:51.819Z"}