{
  "type": "market-data",
  "date": "2026-06-06",
  "nickname": null,
  "content": "[\n  {\n    \"date\": \"2026-06-02\",\n    \"sector\": \"Basic Materials\",\n    \"exchange\": \"NASDAQ\",\n    \"averageChange\": 0.7286703925672988\n  },\n  {\n    \"date\": \"2026-06-05\",\n    \"sector\": \"Communication Services\",\n    \"exchange\": \"NASDAQ\",\n    \"averageChange\": -1.4069771813998266\n  },\n  {\n    \"date\": \"2026-06-02\",\n    \"sector\": \"Consumer Cyclical\",\n    \"exchange\": \"NASDAQ\",\n    \"averageChange\": 0.1500584133084626\n  },\n  {\n    \"date\": \"2026-06-04\",\n    \"sector\": \"Consumer Defensive\",\n    \"exchange\": \"NASDAQ\",\n    \"averageChange\": -1.4286887851424845\n  },\n  {\n    \"date\": \"2026-06-02\",\n    \"sector\": \"Energy\",\n    \"exchange\": \"NASDAQ\",\n    \"averageChange\": 2.691071656547006\n  },\n  {\n    \"date\": \"2026-06-05\",\n    \"sector\": \"Financial Services\",\n    \"exchange\": \"NASDAQ\",\n    \"averageChange\": -0.17772464986182124\n  },\n  {\n    \"date\": \"2026-06-05\",\n    \"sector\": \"Healthcare\",\n    \"exchange\": \"NASDAQ\",\n    \"averageChange\": 0.19238185564771637\n  },\n  {\n    \"date\": \"2026-06-03\",\n    \"sector\": \"Industrials\",\n    \"exchange\": \"NASDAQ\",\n    \"averageChange\": 0.33142123473015594\n  },\n  {\n    \"date\": \"2026-06-04\",\n    \"sector\": \"Real Estate\",\n    \"exchange\": \"NASDAQ\",\n    \"averageChange\": 0.8463087867136565\n  },\n  {\n    \"date\": \"2026-06-05\",\n    \"sector\": \"Technology\",\n    \"exchange\": \"NASDAQ\",\n    \"averageChange\": -4.508355275457876\n  },\n  {\n    \"date\": \"2026-06-03\",\n    \"sector\": \"Utilities\",\n    \"exchange\": \"NASDAQ\",\n    \"averageChange\": -1.4518581690817767\n  }\n] {\"status\":\"ok\",\"totalResults\":351,\"articles\":[{\"source\":{\"id\":null,\"name\":\"The Straits Times\"},\"author\":null,\"title\":\"‘Sell Indonesia’ sweeps trading desks as Prabowo tightens grip\",\"description\":\"The rupiah has slumped while the benchmark stock index has tumbled 36 per cent to become world's worst performing. Read more at straitstimes.com. Read more at straitstimes.com.\",\"url\":\"https://www.straitstimes.com/business/companies-markets/sell-indonesia-sweeps-trading-desks-as-prabowo-tightens-grip\",\"urlToImage\":\"https://cassette.sphdigital.com.sg/image/straitstimes/bbc6271b0249b53c8e0bc3569f0861dbc85d84a8ba63e310ba83be422ad44145\",\"publishedAt\":\"2026-06-05T01:28:42Z\",\"content\":\"JAKARTA Global investors are rapidly losing confidence in Indonesia as the nations stocks tumble at the fastest pace worldwide and its currency sinks to all-time lows.\\r\\nJust five months after hitting… [+7695 chars]\"},{\"source\":{\"id\":null,\"name\":\"Investopedia\"},\"author\":\"Colin Laidley\",\"title\":\"AI Spending Has Been Huge. Now It Could Be Entering a 'Rational' Phase. Is That Good for Markets?\",\"description\":\"Alphabet this week began selling more than $85 billion of stock to raise money for its AI investments, a move that some experts say signals the data center...\",\"url\":\"https://www.investopedia.com/ai-spending-has-been-huge-now-it-could-be-entering-a-rational-phase-is-that-good-for-markets-11990883\",\"urlToImage\":\"https://s.yimg.com/ny/api/res/1.2/FrlX1dNIodDRviNVzCvAVw--/YXBwaWQ9aGlnaGxhbmRlcjt3PTEyMDA7aD05MDA-/https://media.zenfs.com/en/investopedia_245/bcc43335594d702d7ccc54aac82f805e\",\"publishedAt\":\"2026-06-04T16:56:39Z\",\"content\":\"Google parent Alphabet on Monday announced plans to sell stock to fund AI investments.Credit: VCG / VCG via Getty Images\\r\\nKey Takeaways\\r\\n<ul><li>Alphabet this week began selling stock to raise money … [+4695 chars]\"},{\"source\":{\"id\":null,\"name\":\"Yahoo Entertainment\"},\"author\":\"Rinna Diamantakos\",\"title\":\"Economy will be fine ‘if the world continues to remain as optimistic,’ Goldman Sachs CEO says as AI giants plan IPOs\",\"description\":\"Greed will keep the economy going as the AI giants mature, David Solomon says — as long as it doesn’t turn into fear.\",\"url\":\"https://finance.yahoo.com/economy/policy/articles/economy-fine-world-continues-remain-153000120.html\",\"urlToImage\":\"https://s.yimg.com/ny/api/res/1.2/9Sk81ufmJNNDwzPzBrZC1Q--/YXBwaWQ9aGlnaGxhbmRlcjt3PTEyMDA7aD02NzY-/https://media.zenfs.com/en/moneywise_327/7e3930844a01577b60375328c944ec6b\",\"publishedAt\":\"2026-06-04T15:30:00Z\",\"content\":\"Goldman Sachs CEO David Solomon says he believes theres enough greed from investors to absorb the shock of some of the worlds largest tech companies going public.\\r\\nIn an interview with CNBCs Leslie P… [+4755 chars]\"},{\"source\":{\"id\":null,\"name\":\"Protothema.gr\"},\"author\":\"Newsroom\",\"title\":\"The story of a photo and Adonis’ major trolling, Nikos A. is holding meetings (what is he thinking?), the Hatzivasileiou position, CVC is selling the marinas\",\"description\":\"New records for Motor Oil and HELLENiQ ENERGY & the strong language from S. Theodoropoulos\\nThe post The story of a photo and Adonis’ major trolling, Nikos A. is holding meetings (what is he thinking?), the Hatzivasileiou position, CVC is selling the marinas a…\",\"url\":\"https://en.protothema.gr/2026/06/04/the-story-of-a-photo-and-adonis-major-trolling-nikos-a-is-holding-meetings-what-is-he-thinking-the-hatzivasileiou-position-cvc-is-selling-the-marinas/\",\"urlToImage\":\"https://en.protothema.gr/wp-content/uploads/2024/06/ProtothemaEn.png\",\"publishedAt\":\"2026-06-04T12:33:00Z\",\"content\":\"Hello, Ill start with a little behind-the-scenes story that was discussed and read into more than anything else the other night: the photo of Adonis at an event marking Masoutis 50th anniversary, sit… [+28021 chars]\"},{\"source\":{\"id\":\"the-irish-times\",\"name\":\"The Irish Times\"},\"author\":\"Cliff Taylor\",\"title\":\"A dozen questions still to be answered about the Government’s new savings plan\",\"description\":\"The planned savings scheme has been much heralded but numerous details are still unclear\",\"url\":\"https://www.irishtimes.com/your-money/2026/06/04/a-dozen-questions-still-to-be-answered-about-the-governments-new-savings-plan/\",\"urlToImage\":\"https://www.irishtimes.com/resizer/v2/H4T2MS6BQZFBXK66H3ABO4POWU.jpg?smart=true&auth=0f1cfcb6102b21709a469ee785b7faa0ed29873db27c74e320decf2edbda6331&width=1200&height=630\",\"publishedAt\":\"2026-06-04T11:30:43Z\",\"content\":\"Rarely has any policy proposal been subject to so much debate before its details were announced. The early flagging by Minister for Finance Simon Harris about his intention to introduce a new savings… [+9509 chars]\"}]} {\"symbol\":\"SCAG\",\"price\":0.8431,\"name\":\"Scage Future American Depositary Shares\",\"change\":0.5569,\"changesPercentage\":194.58421,\"exchange\":\"NASDAQ\"}, {\"symbol\":\"SPHL\",\"price\":5.35,\"name\":\"Springview Holdings Ltd Class A Ordinary Shares\",\"change\":2.961,\"changesPercentage\":123.94307,\"exchange\":\"NASDAQ\"}, {\"symbol\":\"NOTV\",\"price\":0.1661,\"name\":\"Inotiv, Inc.\",\"change\":0.0795,\"changesPercentage\":91.80139,\"exchange\":\"NASDAQ\"}, {\"symbol\":\"RMSG\",\"price\":1.83,\"name\":\"Real Messenger Corporation\",\"change\":0.73,\"changesPercentage\":66.36364,\"exchange\":\"NASDAQ\"}, {\"symbol\":\"STI\",\"price\":35.72,\"name\":\"Solidion Technology Inc.\",\"change\":13.01,\"changesPercentage\":57.28754,\"exchange\":\"NASDAQ\"}, {\"symbol\":\"BGMS\",\"price\":1.5,\"name\":\"Bio Green Med Solution, Inc.\",\"change\":0.44,\"changesPercentage\":41.50943,\"exchange\":\"NASDAQ\"}, {\"symbol\":\"SUGP\",\"price\":0.9956,\"name\":\"SU Group Holdings Limited Ordinary Shares\",\"change\":0.2792,\"changesPercentage\":38.97264,\"exchange\":\"NASDAQ\"}, {\"symbol\":\"ELOG\",\"price\":1.21,\"name\":\"Eastern International Ltd. Ordinary Shares\",\"change\":0.3346,\"changesPercentage\":38.22253,\"exchange\":\"NASDAQ\"}, {\"symbol\":\"CMND\",\"price\":3.98,\"name\":\"Clearmind Medicine Inc.\",\"change\":1.07,\"changesPercentage\":36.76976,\"exchange\":\"NASDAQ\"}, {\"symbol\":\"SNBR\",\"price\":0.4776,\"name\":\"Sleep Number Corporation\",\"change\":0.1275,\"changesPercentage\":36.41817,\"exchange\":\"NASDAQ\"}, {\"symbol\":\"BNAI\",\"price\":22.17,\"name\":\"Brand Engagement Network, Inc.\",\"change\":5.83,\"changesPercentage\":35.67931,\"exchange\":\"NASDAQ\"}, {\"symbol\":\"YXT\",\"price\":0.543,\"name\":\"Yxt.Com Group Holding Ltd\",\"change\":0.131,\"changesPercentage\":31.79612,\"exchange\":\"NASDAQ\"}, {\"symbol\":\"SOXS\",\"price\":6.84,\"name\":\"Direxion Daily Semiconductor Bear 3X ETF\",\"change\":1.64,\"changesPercentage\":31.53846,\"exchange\":\"AMEX\"}, {\"symbol\":\"BBCP\",\"price\":10.43,\"name\":\"Concrete Pumping Holdings, Inc.\",\"change\":2.45,\"changesPercentage\":30.70175,\"exchange\":\"NASDAQ\"}, {\"symbol\":\"RIBBR\",\"price\":0.23,\"name\":\"Ribbon Acquisition Corp Rights\",\"change\":0.054,\"changesPercentage\":30.68182,\"exchange\":\"NASDAQ\"}, {\"symbol\":\"RGTZ\",\"price\":3.92,\"name\":\"Daily Target 2X Short RGTZ ETF\",\"change\":0.87,\"changesPercentage\":28.52459,\"exchange\":\"NASDAQ\"}, {\"symbol\":\"QBTZ\",\"price\":4.82,\"name\":\"Defiance Daily Target 2X Short QBTS ETF\",\"change\":1.05,\"changesPercentage\":27.85146,\"exchange\":\"NASDAQ\"}, {\"symbol\":\"SMTK\",\"price\":0.4087,\"name\":\"SmartKem, Inc.\",\"change\":0.0887,\"changesPercentage\":27.71875,\"exchange\":\"NASDAQ\"}, {\"symbol\":\"IONZ\",\"price\":2.73,\"name\":\"Daily Target 2X Short IONQ ETF\",\"change\":0.58,\"changesPercentage\":26.97674,\"exchange\":\"NASDAQ\"}, {\"symbol\":\"GDXD\",\"price\":50.26,\"name\":\"MicroSectors Gold Miners -3X Inverse Leveraged ETNs\",\"change\":10.67,\"changesPercentage\":26.95125,\"exchange\":\"AMEX\"}, {\"symbol\":\"DEVS\",\"price\":0.5801,\"name\":\"DevvStream Corp. Common Stock\",\"change\":0.1231,\"changesPercentage\":26.93654,\"exchange\":\"NASDAQ\"}, {\"symbol\":\"VVOS\",\"price\":0.8645,\"name\":\"Vivos Therapeutics, Inc.\",\"change\":0.172,\"changesPercentage\":24.83755,\"exchange\":\"NASDAQ\"}, {\"symbol\":\"CALC\",\"price\":1.06,\"name\":\"CalciMedica, Inc.\",\"change\":0.2094,\"changesPercentage\":24.61792,\"exchange\":\"NASDAQ\"}, {\"symbol\":\"JLHL\",\"price\":44.8,\"name\":\"Julong Holding Limited Class A Ordinary Shares\",\"change\":8.55,\"changesPercentage\":23.58621,\"exchange\":\"NASDAQ\"}, {\"symbol\":\"HURC\",\"price\":21.13,\"name\":\"Hurco Companies, Inc.\",\"change\":4.01,\"changesPercentage\":23.4229,\"exchange\":\"NASDAQ\"}, {\"symbol\":\"DXST\",\"price\":4.14,\"name\":\"Decent Holding Inc.\",\"change\":0.77,\"changesPercentage\":22.84866,\"exchange\":\"NASDAQ\"}, {\"symbol\":\"ETHD\",\"price\":100.06,\"name\":\"ProShares - UltraShort Ether ETF\",\"change\":18.53,\"changesPercentage\":22.72783,\"exchange\":\"AMEX\"}, {\"symbol\":\"SMCZ\",\"price\":7.16,\"name\":\"Daily Target 2X Short SMCI ETF\",\"change\":1.31,\"changesPercentage\":22.39316,\"exchange\":\"NASDAQ\"}, {\"symbol\":\"LBGJ\",\"price\":1.13,\"name\":\"Li Bang International Corporation Inc. Ordinary Shares\",\"change\":0.1978,\"changesPercentage\":21.21862,\"exchange\":\"NASDAQ\"}, {\"symbol\":\"VACHU\",\"price\":16.8,\"name\":\"Voyager Acquisition Corp Unit\",\"change\":2.9,\"changesPercentage\":20.86331,\"exchange\":\"NASDAQ\"}, {\"symbol\":\"TECS\",\"price\":7.7,\"name\":\"Direxion Daily Technology Bear 3X ETF\",\"change\":1.29,\"changesPercentage\":20.1248,\"exchange\":\"AMEX\"}, {\"symbol\":\"EDZ\",\"price\":18.55,\"name\":\"Direxion Daily MSCI Emerging Markets Bear 3X ETF\",\"change\":3.09,\"changesPercentage\":19.98706,\"exchange\":\"AMEX\"}, {\"symbol\":\"JDST\",\"price\":42.6,\"name\":\"Direxion Daily Junior Gold Miners Index Bear 2X ETF\",\"change\":7.09,\"changesPercentage\":19.96621,\"exchange\":\"AMEX\"}, {\"symbol\":\"AIQD\",\"price\":66.9109,\"name\":\"MicroSectors -3x Short Artificial Intelligence (AI) ETNs\",\"change\":11.1289,\"changesPercentage\":19.9507,\"exchange\":\"AMEX\"}, {\"symbol\":\"MRLN\",\"price\":8.6,\"name\":\"Merlin, Inc.\",\"change\":1.42,\"changesPercentage\":19.77716,\"exchange\":\"NASDAQ\"}, {\"symbol\":\"ACCL\",\"price\":1.55,\"name\":\"Acco Group Holdings Limited Ordinary Shares\",\"change\":0.24,\"changesPercentage\":18.32061,\"exchange\":\"NASDAQ\"}, {\"symbol\":\"BERZ\",\"price\":24.36,\"name\":\"MicroSectors Solactive FANG & Innovation -3X Inverse Leveraged ETN\",\"change\":3.74,\"changesPercentage\":18.13773,\"exchange\":\"AMEX\"}, {\"symbol\":\"HIBS\",\"price\":24.03,\"name\":\"Direxion Daily S&P 500 High Beta Bear 3X ETF\",\"change\":3.68,\"changesPercentage\":18.08354,\"exchange\":\"AMEX\"}, {\"symbol\":\"CURV\",\"price\":1.64,\"name\":\"Torrid Holdings Inc.\",\"change\":0.25,\"changesPercentage\":17.98561,\"exchange\":\"NYSE\"}, {\"symbol\":\"ZSL\",\"price\":24.59,\"name\":\"ProShares - UltraShort Silver\",\"change\":3.64,\"changesPercentage\":17.3747,\"exchange\":\"AMEX\"}, {\"symbol\":\"DUST\",\"price\":61.15,\"name\":\"Direxion Daily Gold Miners Index Bear 2X ETF\",\"change\":9.03,\"changesPercentage\":17.3254,\"exchange\":\"AMEX\"}, {\"symbol\":\"MKLYR\",\"price\":0.22,\"name\":\"McKinley Acquisition Corporation Rights\",\"change\":0.0324,\"changesPercentage\":17.27079,\"exchange\":\"NASDAQ\"}, {\"symbol\":\"MYPS\",\"price\":0.61,\"name\":\"PLAYSTUDIOS, Inc.\",\"change\":0.0898,\"changesPercentage\":17.26259,\"exchange\":\"NASDAQ\"}, {\"symbol\":\"TSXD\",\"price\":7.5,\"name\":\"Direxion Daily Semiconductors Top 5 Bear 2X ETF\",\"change\":1.1,\"changesPercentage\":17.1875,\"exchange\":\"AMEX\"}, {\"symbol\":\"SSG\",\"price\":14.59,\"name\":\"ProShares - UltraShort Semiconductors\",\"change\":2.1,\"changesPercentage\":16.81345,\"exchange\":\"AMEX\"}, {\"symbol\":\"STAK\",\"price\":4.93,\"name\":\"STAK Inc. Ordinary Shares\",\"change\":0.69,\"changesPercentage\":16.27358,\"exchange\":\"NASDAQ\"}, {\"symbol\":\"RKLZ\",\"price\":2.82,\"name\":\"DEFIANCE DAILY TARGET 2X SHORT RKLB ETF\",\"change\":0.39,\"changesPercentage\":16.04938,\"exchange\":\"NASDAQ\"}, {\"symbol\":\"NITO\",\"price\":5.8424,\"name\":\"N2OFF, Inc.\",\"change\":0.7824,\"changesPercentage\":15.46245,\"exchange\":\"NASDAQ\"}, {\"symbol\":\"MSDD\",\"price\":53.8316,\"name\":\"GraniteShares 2x Short MSTR Daily ETF\",\"change\":7.1966,\"changesPercentage\":15.43176,\"exchange\":\"NASDAQ\"}, {\"symbol\":\"BESS\",\"price\":3.52,\"name\":\"Bimergen Energy Corporation\",\"change\":0.47,\"changesPercentage\":15.40984,\"exchange\":\"AMEX\"} {\"symbol\":\"NUWE\",\"price\":0.1672,\"name\":\"Nuwellis, Inc.\",\"change\":-0.2638,\"changesPercentage\":-61.2065,\"exchange\":\"NASDAQ\"}, {\"symbol\":\"NYXH\",\"price\":1.45,\"name\":\"Nyxoah S.A.\",\"change\":-1.43,\"changesPercentage\":-49.65278,\"exchange\":\"NASDAQ\"}, {\"symbol\":\"EGG\",\"price\":5.6,\"name\":\"Enigmatig Limited\",\"change\":-5.25,\"changesPercentage\":-48.3871,\"exchange\":\"AMEX\"}, {\"symbol\":\"CYPH\",\"price\":0.5188,\"name\":\"Cypherpunk Technologies Inc.\",\"change\":-0.4626,\"changesPercentage\":-47.13674,\"exchange\":\"NASDAQ\"}, {\"symbol\":\"KORU\",\"price\":610.01,\"name\":\"Direxion Daily MSCI South Korea Bull 3X ETF\",\"change\":-439.69,\"changesPercentage\":-41.88721,\"exchange\":\"AMEX\"}, {\"symbol\":\"TDIC\",\"price\":0.224,\"name\":\"Dreamland Limited Class A Ordinary Shares\",\"change\":-0.1414,\"changesPercentage\":-38.69732,\"exchange\":\"NASDAQ\"}, {\"symbol\":\"AMPGR\",\"price\":0.79,\"name\":\"Amplitech Group, Inc. Series A Right\",\"change\":-0.491,\"changesPercentage\":-38.32943,\"exchange\":\"NASDAQ\"}, {\"symbol\":\"FOFO\",\"price\":3.9,\"name\":\"Hang Feng Technology Innovation Co., Ltd. Ordinary Shares\",\"change\":-2.28,\"changesPercentage\":-36.8932,\"exchange\":\"NASDAQ\"}, {\"symbol\":\"TROO\",\"price\":2.24,\"name\":\"TROOPS, Inc.\",\"change\":-1.21,\"changesPercentage\":-35.07246,\"exchange\":\"NASDAQ\"}, {\"symbol\":\"VLN\",\"price\":2.11,\"name\":\"Valens Semiconductor Ltd.\",\"change\":-1.12,\"changesPercentage\":-34.67492,\"exchange\":\"NYSE\"}, {\"symbol\":\"CDTG\",\"price\":3.18,\"name\":\"CDT Environmental Technology Investment Holdings Limited ordinary shares\",\"change\":-1.67,\"changesPercentage\":-34.43299,\"exchange\":\"NASDAQ\"}, {\"symbol\":\"MRVU\",\"price\":195.24,\"name\":\"Direxion Daily MRVL Bull 2X ETF\",\"change\":-100.15,\"changesPercentage\":-33.90433,\"exchange\":\"NASDAQ\"}, {\"symbol\":\"DXF\",\"price\":0.5578,\"name\":\"Eason Technology Limited\",\"change\":-0.2767,\"changesPercentage\":-33.15758,\"exchange\":\"AMEX\"}, {\"symbol\":\"MVLL\",\"price\":148.59,\"name\":\"GraniteShares 2x Long MRVL Daily ETF\",\"change\":-73.63,\"changesPercentage\":-33.13383,\"exchange\":\"NASDAQ\"}, {\"symbol\":\"WCT\",\"price\":1.41,\"name\":\"Wellchange Holdings Company Limited\",\"change\":-0.69,\"changesPercentage\":-32.85714,\"exchange\":\"NASDAQ\"}, {\"symbol\":\"AMPGZ\",\"price\":0.97,\"name\":\"Amplitech Group, Inc. Series B Right\",\"change\":-0.46,\"changesPercentage\":-32.16783,\"exchange\":\"NASDAQ\"}, {\"symbol\":\"EPSM\",\"price\":1.13,\"name\":\"Epsium Enterprise Limited Ordinary Shares\",\"change\":-0.53,\"changesPercentage\":-31.92771,\"exchange\":\"NASDAQ\"}, {\"symbol\":\"QSU\",\"price\":14.41,\"name\":\"Daily Target 2X Long QS ETF\",\"change\":-6.66,\"changesPercentage\":-31.60892,\"exchange\":\"AMEX\"}, {\"symbol\":\"SOXL\",\"price\":182.54,\"name\":\"Direxion Daily Semiconductor Bull 3X ETF\",\"change\":-80.16,\"changesPercentage\":-30.51389,\"exchange\":\"AMEX\"}, {\"symbol\":\"RGTX\",\"price\":22.94,\"name\":\"Daily Target 2X Long RGTI ETF\",\"change\":-9.501,\"changesPercentage\":-29.28701,\"exchange\":\"NASDAQ\"}, {\"symbol\":\"RCAX\",\"price\":9.5,\"name\":\"Daily Target 2X Long RCAT ETF\",\"change\":-3.7,\"changesPercentage\":-28.0303,\"exchange\":\"NASDAQ\"}, {\"symbol\":\"LIQT\",\"price\":0.88,\"name\":\"LiqTech International, Inc.\",\"change\":-0.33,\"changesPercentage\":-27.27273,\"exchange\":\"NASDAQ\"}, {\"symbol\":\"IONL\",\"price\":32.95,\"name\":\"GraniteShares 2x Long IONQ Daily ETF\",\"change\":-12.22,\"changesPercentage\":-27.05335,\"exchange\":\"NASDAQ\"}, {\"symbol\":\"IONX\",\"price\":62.24,\"name\":\"Daily Target 2X Long IONQ ETF\",\"change\":-22.99,\"changesPercentage\":-26.97407,\"exchange\":\"NASDAQ\"}, {\"symbol\":\"GDXU\",\"price\":104.19,\"name\":\"MicroSectors Gold Miners 3X Leveraged ETN\",\"change\":-38.07,\"changesPercentage\":-26.76086,\"exchange\":\"AMEX\"}, {\"symbol\":\"MUU\",\"price\":661.33,\"name\":\"Direxion Daily MU Bull 2X ETF\",\"change\":-240.23,\"changesPercentage\":-26.64604,\"exchange\":\"NASDAQ\"}, {\"symbol\":\"MULL\",\"price\":579,\"name\":\"GraniteShares 2x Long MU Daily ETF\",\"change\":-206.55,\"changesPercentage\":-26.29368,\"exchange\":\"NASDAQ\"}, {\"symbol\":\"HAO\",\"price\":0.8847,\"name\":\"Haoxi Health Technology Limited\",\"change\":-0.3153,\"changesPercentage\":-26.275,\"exchange\":\"NASDAQ\"}, {\"symbol\":\"UUUG\",\"price\":5.93,\"name\":\"Leverage Shares 2x Long UUUU Daily ETF\",\"change\":-2.1015,\"changesPercentage\":-26.16572,\"exchange\":\"NASDAQ\"}, {\"symbol\":\"ARMG\",\"price\":39.69,\"name\":\"Leverage Shares 2x Long ARM Daily ETF\",\"change\":-13.95,\"changesPercentage\":-26.00671,\"exchange\":\"NASDAQ\"}, {\"symbol\":\"PL\",\"price\":32.22,\"name\":\"Planet Labs PBC\",\"change\":-11.31,\"changesPercentage\":-25.98208,\"exchange\":\"NYSE\"}, {\"symbol\":\"ZUMZ\",\"price\":17.39,\"name\":\"Zumiez Inc.\",\"change\":-6.09,\"changesPercentage\":-25.93697,\"exchange\":\"NASDAQ\"}, {\"symbol\":\"GLGG\",\"price\":7.0833,\"name\":\"Leverage Shares 2x Long GLXY Daily ETF\",\"change\":-2.4367,\"changesPercentage\":-25.59559,\"exchange\":\"NASDAQ\"}, {\"symbol\":\"VIDA\",\"price\":4.05,\"name\":\"VIDA Global Inc.\",\"change\":-1.39,\"changesPercentage\":-25.55147,\"exchange\":\"AMEX\"}, {\"symbol\":\"FABC\",\"price\":4.25,\"name\":\"StableX Technologies, Inc.\",\"change\":-1.45,\"changesPercentage\":-25.4386,\"exchange\":\"NASDAQ\"}, {\"symbol\":\"SBEV\",\"price\":0.25,\"name\":\"Splash Beverage Group, Inc.\",\"change\":-0.0845,\"changesPercentage\":-25.26158,\"exchange\":\"AMEX\"}, {\"symbol\":\"TDTH\",\"price\":2.37,\"name\":\"Trident Digital Tech Holdings Ltd\",\"change\":-0.79,\"changesPercentage\":-25,\"exchange\":\"NASDAQ\"}, {\"symbol\":\"OPTT\",\"price\":0.2913,\"name\":\"Ocean Power Technologies, Inc.\",\"change\":-0.0967,\"changesPercentage\":-24.92268,\"exchange\":\"AMEX\"}, {\"symbol\":\"HERE\",\"price\":1.78,\"name\":\"Here Group Limited\",\"change\":-0.59,\"changesPercentage\":-24.89451,\"exchange\":\"NASDAQ\"}, {\"symbol\":\"GPUS\",\"price\":0.151,\"name\":\"Hyperscale Data, Inc.\",\"change\":-0.0499,\"changesPercentage\":-24.83823,\"exchange\":\"AMEX\"}, {\"symbol\":\"ATLN\",\"price\":0.9799,\"name\":\"Atlantic International Corp.\",\"change\":-0.3201,\"changesPercentage\":-24.62308,\"exchange\":\"NASDAQ\"}, {\"symbol\":\"CIFG\",\"price\":12.2358,\"name\":\"Leverage Shares 2X Long CIFR Daily ETF\",\"change\":-3.9842,\"changesPercentage\":-24.5635,\"exchange\":\"NASDAQ\"}, {\"symbol\":\"CANG\",\"price\":0.31465,\"name\":\"Cango Inc.\",\"change\":-0.10235,\"changesPercentage\":-24.54436,\"exchange\":\"NYSE\"}, {\"symbol\":\"NBIL\",\"price\":40.91,\"name\":\"GraniteShares 2x Long NBIS Daily ETF\",\"change\":-13.3,\"changesPercentage\":-24.53422,\"exchange\":\"NASDAQ\"}, {\"symbol\":\"IRE\",\"price\":25.73,\"name\":\"Daily Target 2X Long IREN ETF\",\"change\":-8.33,\"changesPercentage\":-24.45684,\"exchange\":\"AMEX\"}, {\"symbol\":\"NBIG\",\"price\":28.6,\"name\":\"Leverage Shares 2x Long NBIS Daily ETF\",\"change\":-9.24,\"changesPercentage\":-24.4186,\"exchange\":\"NASDAQ\"}, {\"symbol\":\"BAIG\",\"price\":34.7,\"name\":\"Leverage Shares 2x Long BBAI Daily ETF\",\"change\":-11.11,\"changesPercentage\":-24.25235,\"exchange\":\"NASDAQ\"}, {\"symbol\":\"QTEX\",\"price\":1.42,\"name\":\"QTREX Quantum Ltd.\",\"change\":-0.45,\"changesPercentage\":-24.06417,\"exchange\":\"NASDAQ\"}, {\"symbol\":\"TERG\",\"price\":46.16,\"name\":\"Leverage Shares 2x Long TER Daily ETF\",\"change\":-14.62,\"changesPercentage\":-24.05397,\"exchange\":\"NASDAQ\"}, {\"symbol\":\"IREG\",\"price\":19.64,\"name\":\"Leverage Shares 2x Long IREN Daily ETF\",\"change\":-6.18,\"changesPercentage\":-23.93493,\"exchange\":\"NASDAQ\"}  {\"rss\":{\"_attributes\":{\"xmlns:dc\":\"http://purl.org/dc/elements/1.1/\",\"version\":\"2.0\"},\"channel\":[{\"title\":[\"All Articles on Seeking Alpha\"],\"description\":[\"© seekingalpha.com. Use of this feed is limited to personal, non-commercial use and is governed by Seeking Alpha's Terms of Use (https://about.seekingalpha.com/terms). Publishing this feed for public or commercial use and/or misrepresentation by a third party is prohibited.\"],\"author\":[{\"name\":[\"SeekingAlpha.com\"]}],\"link\":[\"https://seekingalpha.com\"],\"item\":[{\"title\":[\"COPT Defense Properties: Unique Property Niche Makes Shares A Gem\"],\"link\":[\"https://seekingalpha.com/article/4912546-copt-defense-properties-unique-property-niche-makes-shares-a-hidden-gem?source=feed_all_articles\"],\"guid\":[{\"_value\":\"4912546\",\"_attributes\":{\"isPermaLink\":\"false\"}}],\"pubDate\":[\"Fri, 05 Jun 2026 22:45:00 -0400\"],\"category\":[{\"_value\":\"CDP\",\"_attributes\":{\"type\":\"symbol\",\"link\":\"https://seekingalpha.com/symbol/CDP\"}},{\"_value\":\"Seeking Profits\",\"_attributes\":{\"type\":\"author\",\"link\":\"https://seekingalpha.com/author/seeking-profits\"}}]},{\"title\":[\"WisdomTree Model Portfolio Positioning Update\"],\"link\":[\"https://seekingalpha.com/article/4912550-wisdomtree-model-portfolio-positioning-update?source=feed_all_articles\"],\"guid\":[{\"_value\":\"4912550\",\"_attributes\":{\"isPermaLink\":\"false\"}}],\"pubDate\":[\"Fri, 05 Jun 2026 22:35:00 -0400\"],\"category\":[{\"_value\":\"QGRW\",\"_attributes\":{\"type\":\"symbol\",\"link\":\"https://seekingalpha.com/symbol/QGRW\"}},{\"_value\":\"WTV\",\"_attributes\":{\"type\":\"symbol\",\"link\":\"https://seekingalpha.com/symbol/WTV\"}},{\"_value\":\"WisdomTree\",\"_attributes\":{\"type\":\"author\",\"link\":\"https://seekingalpha.com/author/wisdomtree\"}}]},{\"title\":[\"KBA Tells The Story Of China's Equity Market Evolution\"],\"link\":[\"https://seekingalpha.com/article/4912549-kba-tells-the-story-of-chinas-equity-market-evolution?source=feed_all_articles\"],\"guid\":[{\"_value\":\"4912549\",\"_attributes\":{\"isPermaLink\":\"false\"}}],\"pubDate\":[\"Fri, 05 Jun 2026 22:20:00 -0400\"],\"category\":[{\"_value\":\"KBA\",\"_attributes\":{\"type\":\"symbol\",\"link\":\"https://seekingalpha.com/symbol/KBA\"}},{\"_value\":\"KraneShares\",\"_attributes\":{\"type\":\"author\",\"link\":\"https://seekingalpha.com/author/kraneshares\"}}]},{\"title\":[\"Asset Quality Concerns Linger For Hingham Institution For Savings\"],\"link\":[\"https://seekingalpha.com/article/4912544-asset-quality-concerns-linger-for-hingham-institution-for-savings?source=feed_all_articles\"],\"guid\":[{\"_value\":\"4912544\",\"_attributes\":{\"isPermaLink\":\"false\"}}],\"pubDate\":[\"Fri, 05 Jun 2026 22:07:10 -0400\"],\"category\":[{\"_value\":\"HIFS\",\"_attributes\":{\"type\":\"symbol\",\"link\":\"https://seekingalpha.com/symbol/HIFS\"}},{\"_value\":\"Crimson And Gold Research\",\"_attributes\":{\"type\":\"author\",\"link\":\"https://seekingalpha.com/author/crimson-and-gold-research\"}}]},{\"title\":[\"ABM Industries Incorporated 2026 Q2 - Results - Earnings Call Presentation\"],\"link\":[\"https://seekingalpha.com/article/4912547-abm-industries-incorporated-2026-q2-results-earnings-call-presentation?source=feed_all_articles\"],\"guid\":[{\"_value\":\"4912547\",\"_attributes\":{\"isPermaLink\":\"false\"}}],\"pubDate\":[\"Fri, 05 Jun 2026 22:00:37 -0400\"],\"category\":[{\"_value\":\"ABM\",\"_attributes\":{\"type\":\"symbol\",\"link\":\"https://seekingalpha.com/symbol/ABM\"}},{\"_value\":\"SA Transcripts\",\"_attributes\":{\"type\":\"author\",\"link\":\"https://seekingalpha.com/author/sa-transcripts\"}}]},{\"title\":[\"Arista Networks: TAM Expansion And Surging AI Demand\"],\"link\":[\"https://seekingalpha.com/article/4912543-arista-networks-tam-expansion-and-surging-ai-demand?source=feed_all_articles\"],\"guid\":[{\"_value\":\"4912543\",\"_attributes\":{\"isPermaLink\":\"false\"}}],\"pubDate\":[\"Fri, 05 Jun 2026 21:55:23 -0400\"],\"category\":[{\"_value\":\"ANET\",\"_attributes\":{\"type\":\"symbol\",\"link\":\"https://seekingalpha.com/symbol/ANET\"}},{\"_value\":\"Gary Alexander\",\"_attributes\":{\"type\":\"author\",\"link\":\"https://seekingalpha.com/author/gary-alexander\"}}]},{\"title\":[\"BTC: Why Bitcoin May Be Bottoming Now, Levels To Watch\"],\"link\":[\"https://seekingalpha.com/article/4912542-btc-why-bitcoin-may-be-bottoming-now-levels-to-watch?source=feed_all_articles\"],\"guid\":[{\"_value\":\"4912542\",\"_attributes\":{\"isPermaLink\":\"false\"}}],\"pubDate\":[\"Fri, 05 Jun 2026 21:49:21 -0400\"],\"category\":[{\"_value\":\"BTC-USD\",\"_attributes\":{\"type\":\"symbol\",\"link\":\"https://seekingalpha.com/symbol/BTC-USD\"}},{\"_value\":\"BTC\",\"_attributes\":{\"type\":\"symbol\",\"link\":\"https://seekingalpha.com/symbol/BTC\"}},{\"_value\":\"Mike Zaccardi, CFA, CMT\",\"_attributes\":{\"type\":\"author\",\"link\":\"https://seekingalpha.com/author/mike-zaccardi-cfa-cmt\"}}]},{\"title\":[\"White Mountains Insurance Group, Ltd. (WTM) Analyst/Investor Day Transcript\"],\"link\":[\"https://seekingalpha.com/article/4912486-white-mountains-insurance-group-ltd-wtm-analyst-investor-day-transcript?source=feed_all_articles\"],\"guid\":[{\"_value\":\"4912486\",\"_attributes\":{\"isPermaLink\":\"false\"}}],\"pubDate\":[\"Fri, 05 Jun 2026 21:22:53 -0400\"],\"category\":[{\"_value\":\"WTM\",\"_attributes\":{\"type\":\"symbol\",\"link\":\"https://seekingalpha.com/symbol/WTM\"}},{\"_value\":\"SA Transcripts\",\"_attributes\":{\"type\":\"author\",\"link\":\"https://seekingalpha.com/author/sa-transcripts\"}}]},{\"title\":[\"Northeast Community Bancorp: A Buy As Deposit Inflows Continue In Q1 2026\"],\"link\":[\"https://seekingalpha.com/article/4912512-northeast-community-bancorp-a-buy-as-deposit-inflows-continue-in-q1-2026?source=feed_all_articles\"],\"guid\":[{\"_value\":\"4912512\",\"_attributes\":{\"isPermaLink\":\"false\"}}],\"pubDate\":[\"Fri, 05 Jun 2026 19:58:06 -0400\"],\"category\":[{\"_value\":\"IYF\",\"_attributes\":{\"type\":\"symbol\",\"link\":\"https://seekingalpha.com/symbol/IYF\"}},{\"_value\":\"IAT\",\"_attributes\":{\"type\":\"symbol\",\"link\":\"https://seekingalpha.com/symbol/IAT\"}},{\"_value\":\"NECB\",\"_attributes\":{\"type\":\"symbol\",\"link\":\"https://seekingalpha.com/symbol/NECB\"}},{\"_value\":\"Ivo Kolchev\",\"_attributes\":{\"type\":\"author\",\"link\":\"https://seekingalpha.com/author/ivo-kolchev\"}}]},{\"title\":[\"Employment Report: 172K Jobs Added In May, Higher Than Expected\"],\"link\":[\"https://seekingalpha.com/article/4912539-employment-report-172k-jobs-added-in-may-higher-than-expected?source=feed_all_articles\"],\"guid\":[{\"_value\":\"4912539\",\"_attributes\":{\"isPermaLink\":\"false\"}}],\"pubDate\":[\"Fri, 05 Jun 2026 19:45:00 -0400\"],\"category\":[{\"_value\":\"IVV\",\"_attributes\":{\"type\":\"symbol\",\"link\":\"https://seekingalpha.com/symbol/IVV\"}},{\"_value\":\"SPY\",\"_attributes\":{\"type\":\"symbol\",\"link\":\"https://seekingalpha.com/symbol/SPY\"}},{\"_value\":\"VOO\",\"_attributes\":{\"type\":\"symbol\",\"link\":\"https://seekingalpha.com/symbol/VOO\"}},{\"_value\":\"SPYM\",\"_attributes\":{\"type\":\"symbol\",\"link\":\"https://seekingalpha.com/symbol/SPYM\"}},{\"_value\":\"AFMC\",\"_attributes\":{\"type\":\"symbol\",\"link\":\"https://seekingalpha.com/symbol/AFMC\"}},{\"_value\":\"AFSM\",\"_attributes\":{\"type\":\"symbol\",\"link\":\"https://seekingalpha.com/symbol/AFSM\"}},{\"_value\":\"ARKK\",\"_attributes\":{\"type\":\"symbol\",\"link\":\"https://seekingalpha.com/symbol/ARKK\"}},{\"_value\":\"AVUV\",\"_attributes\":{\"type\":\"symbol\",\"link\":\"https://seekingalpha.com/symbol/AVUV\"}},{\"_value\":\"BAPR\",\"_attributes\":{\"type\":\"symbol\",\"link\":\"https://seekingalpha.com/symbol/BAPR\"}},{\"_value\":\"IVOO\",\"_attributes\":{\"type\":\"symbol\",\"link\":\"https://seekingalpha.com/symbol/IVOO\"}},{\"_value\":\"IVOV\",\"_attributes\":{\"type\":\"symbol\",\"link\":\"https://seekingalpha.com/symbol/IVOV\"}},{\"_value\":\"IVW\",\"_attributes\":{\"type\":\"symbol\",\"link\":\"https://seekingalpha.com/symbol/IVW\"}},{\"_value\":\"IWC\",\"_attributes\":{\"type\":\"symbol\",\"link\":\"https://seekingalpha.com/symbol/IWC\"}},{\"_value\":\"IWM\",\"_attributes\":{\"type\":\"symbol\",\"link\":\"https://seekingalpha.com/symbol/IWM\"}},{\"_value\":\"IWN\",\"_attributes\":{\"type\":\"symbol\",\"link\":\"https://seekingalpha.com/symbol/IWN\"}},{\"_value\":\"IWO\",\"_attributes\":{\"type\":\"symbol\",\"link\":\"https://seekingalpha.com/symbol/IWO\"}},{\"_value\":\"IWP\",\"_attributes\":{\"type\":\"symbol\",\"link\":\"https://seekingalpha.com/symbol/IWP\"}},{\"_value\":\"IWR\",\"_attributes\":{\"type\":\"symbol\",\"link\":\"https://seekingalpha.com/symbol/IWR\"}},{\"_value\":\"IWS\",\"_attributes\":{\"type\":\"symbol\",\"link\":\"https://seekingalpha.com/symbol/IWS\"}},{\"_value\":\"IYY\",\"_attributes\":{\"type\":\"symbol\",\"link\":\"https://seekingalpha.com/symbol/IYY\"}},{\"_value\":\"QQQ\",\"_attributes\":{\"type\":\"symbol\",\"link\":\"https://seekingalpha.com/symbol/QQQ\"}},{\"_value\":\"SPLV\",\"_attributes\":{\"type\":\"symbol\",\"link\":\"https://seekingalpha.com/symbol/SPLV\"}},{\"_value\":\"SPMD\",\"_attributes\":{\"type\":\"symbol\",\"link\":\"https://seekingalpha.com/symbol/SPMD\"}},{\"_value\":\"SPMO\",\"_attributes\":{\"type\":\"symbol\",\"link\":\"https://seekingalpha.com/symbol/SPMO\"}},{\"_value\":\"SPSM\",\"_attributes\":{\"type\":\"symbol\",\"link\":\"https://seekingalpha.com/symbol/SPSM\"}},{\"_value\":\"SPUS\",\"_attributes\":{\"type\":\"symbol\",\"link\":\"https://seekingalpha.com/symbol/SPUS\"}},{\"_value\":\"SPUU\",\"_attributes\":{\"type\":\"symbol\",\"link\":\"https://seekingalpha.com/symbol/SPUU\"}},{\"_value\":\"SPVM\",\"_attributes\":{\"type\":\"symbol\",\"link\":\"https://seekingalpha.com/symbol/SPVM\"}},{\"_value\":\"QVMT\",\"_attributes\":{\"type\":\"symbol\",\"link\":\"https://seekingalpha.com/symbol/QVMT\"}},{\"_value\":\"SPXE\",\"_attributes\":{\"type\":\"symbol\",\"link\":\"https://seekingalpha.com/symbol/SPXE\"}},{\"_value\":\"SPXL\",\"_attributes\":{\"type\":\"symbol\",\"link\":\"https://seekingalpha.com/symbol/SPXL\"}},{\"_value\":\"SPXN\",\"_attributes\":{\"type\":\"symbol\",\"link\":\"https://seekingalpha.com/symbol/SPXN\"}},{\"_value\":\"SPXS\",\"_attributes\":{\"type\":\"symbol\",\"link\":\"https://seekingalpha.com/symbol/SPXS\"}},{\"_value\":\"SPXT\",\"_attributes\":{\"type\":\"symbol\",\"link\":\"https://seekingalpha.com/symbol/SPXT\"}},{\"_value\":\"SPXU\",\"_attributes\":{\"type\":\"symbol\",\"link\":\"https://seekingalpha.com/symbol/SPXU\"}},{\"_value\":\"SPXV\",\"_attributes\":{\"type\":\"symbol\",\"link\":\"https://seekingalpha.com/symbol/SPXV\"}},{\"_value\":\"SPYD\",\"_attributes\":{\"type\":\"symbol\",\"link\":\"https://seekingalpha.com/symbol/SPYD\"}},{\"_value\":\"SPYG\",\"_attributes\":{\"type\":\"symbol\",\"link\":\"https://seekingalpha.com/symbol/SPYG\"}},{\"_value\":\"SPYV\",\"_attributes\":{\"type\":\"symbol\",\"link\":\"https://seekingalpha.com/symbol/SPYV\"}},{\"_value\":\"SPYX\",\"_attributes\":{\"type\":\"symbol\",\"link\":\"https://seekingalpha.com/symbol/SPYX\"}},{\"_value\":\"SQLV\",\"_attributes\":{\"type\":\"symbol\",\"link\":\"https://seekingalpha.com/symbol/SQLV\"}},{\"_value\":\"SSO\",\"_attributes\":{\"type\":\"symbol\",\"link\":\"https://seekingalpha.com/symbol/SSO\"}},{\"_value\":\"SSPY\",\"_attributes\":{\"type\":\"symbol\",\"link\":\"https://seekingalpha.com/symbol/SSPY\"}},{\"_value\":\"SVAL\",\"_attributes\":{\"type\":\"symbol\",\"link\":\"https://seekingalpha.com/symbol/SVAL\"}},{\"_value\":\"SYLD\",\"_attributes\":{\"type\":\"symbol\",\"link\":\"https://seekingalpha.com/symbol/SYLD\"}},{\"_value\":\"TMDV\",\"_attributes\":{\"type\":\"symbol\",\"link\":\"https://seekingalpha.com/symbol/TMDV\"}},{\"_value\":\"TPHD\",\"_attributes\":{\"type\":\"symbol\",\"link\":\"https://seekingalpha.com/symbol/TPHD\"}},{\"_value\":\"TPLC\",\"_attributes\":{\"type\":\"symbol\",\"link\":\"https://seekingalpha.com/symbol/TPLC\"}},{\"_value\":\"TPSC\",\"_attributes\":{\"type\":\"symbol\",\"link\":\"https://seekingalpha.com/symbol/TPSC\"}},{\"_value\":\"UAUG\",\"_attributes\":{\"type\":\"symbol\",\"link\":\"https://seekingalpha.com/symbol/UAUG\"}},{\"_value\":\"UJAN\",\"_attributes\":{\"type\":\"symbol\",\"link\":\"https://seekingalpha.com/symbol/UJAN\"}},{\"_value\":\"UMAR\",\"_attributes\":{\"type\":\"symbol\",\"link\":\"https://seekingalpha.com/symbol/UMAR\"}},{\"_value\":\"UMAY\",\"_attributes\":{\"type\":\"symbol\",\"link\":\"https://seekingalpha.com/symbol/UMAY\"}},{\"_value\":\"UOCT\",\"_attributes\":{\"type\":\"symbol\",\"link\":\"https://seekingalpha.com/symbol/UOCT\"}},{\"_value\":\"UPRO\",\"_attributes\":{\"type\":\"symbol\",\"link\":\"https://seekingalpha.com/symbol/UPRO\"}},{\"_value\":\"USMC\",\"_attributes\":{\"type\":\"symbol\",\"link\":\"https://seekingalpha.com/symbol/USMC\"}},{\"_value\":\"USMF\",\"_attributes\":{\"type\":\"symbol\",\"link\":\"https://seekingalpha.com/symbol/USMF\"}},{\"_value\":\"USVM\",\"_attributes\":{\"type\":\"symbol\",\"link\":\"https://seekingalpha.com/symbol/USVM\"}},{\"_value\":\"MAGS\",\"_attributes\":{\"type\":\"symbol\",\"link\":\"https://seekingalpha.com/symbol/MAGS\"}},{\"_value\":\"Advisor Perspectives Charts\",\"_attributes\":{\"type\":\"author\",\"link\":\"https://seekingalpha.com/author/advisor-perspectives-charts\"}}]},{\"title\":[\"BTS Rail Mass Transit Growth Infrastructure Fund 2026 Q4 - Results - Earnings Call Presentation\"],\"link\":[\"https://seekingalpha.com/article/4912538-bts-rail-mass-transit-growth-infrastructure-fund-2026-q4-results-earnings-call-presentation?source=feed_all_articles\"],\"guid\":[{\"_value\":\"4912538\",\"_attributes\":{\"isPermaLink\":\"false\"}}],\"pubDate\":[\"Fri, 05 Jun 2026 19:27:52 -0400\"],\"category\":[{\"_value\":\"BTSRF\",\"_attributes\":{\"type\":\"symbol\",\"link\":\"https://seekingalpha.com/symbol/BTSRF\"}},{\"_value\":\"SA Transcripts\",\"_attributes\":{\"type\":\"author\",\"link\":\"https://seekingalpha.com/author/sa-transcripts\"}}]},{\"title\":[\"Kyoritsu Maintenance Co., Ltd. 2026 Q4 - Results - Earnings Call Presentation\"],\"link\":[\"https://seekingalpha.com/article/4912537-kyoritsu-maintenance-co-ltd-2026-q4-results-earnings-call-presentation?source=feed_all_articles\"],\"guid\":[{\"_value\":\"4912537\",\"_attributes\":{\"isPermaLink\":\"false\"}}],\"pubDate\":[\"Fri, 05 Jun 2026 19:27:30 -0400\"],\"category\":[{\"_value\":\"KYMCF\",\"_attributes\":{\"type\":\"symbol\",\"link\":\"https://seekingalpha.com/symbol/KYMCF\"}},{\"_value\":\"SA Transcripts\",\"_attributes\":{\"type\":\"author\",\"link\":\"https://seekingalpha.com/author/sa-transcripts\"}}]},{\"title\":[\"B&M European Value Retail plc 2026 Q4 - Results - Earnings Call Presentation\"],\"link\":[\"https://seekingalpha.com/article/4912536-b-and-m-european-value-retail-plc-2026-q4-results-earnings-call-presentation?source=feed_all_articles\"],\"guid\":[{\"_value\":\"4912536\",\"_attributes\":{\"isPermaLink\":\"false\"}}],\"pubDate\":[\"Fri, 05 Jun 2026 19:27:04 -0400\"],\"category\":[{\"_value\":\"BMRRY\",\"_attributes\":{\"type\":\"symbol\",\"link\":\"https://seekingalpha.com/symbol/BMRRY\"}},{\"_value\":\"BMRPF\",\"_attributes\":{\"type\":\"symbol\",\"link\":\"https://seekingalpha.com/symbol/BMRPF\"}},{\"_value\":\"SA Transcripts\",\"_attributes\":{\"type\":\"author\",\"link\":\"https://seekingalpha.com/author/sa-transcripts\"}}]},{\"title\":[\"Howden Joinery Group Plc (HWDJY) Ultima Furniture Systems Limited - M&A Call - Slideshow\"],\"link\":[\"https://seekingalpha.com/article/4912535-howden-joinery-group-plc-hwdjy-ultima-furniture-systems-limited-m-and-a-call-slideshow?source=feed_all_articles\"],\"guid\":[{\"_value\":\"4912535\",\"_attributes\":{\"isPermaLink\":\"false\"}}],\"pubDate\":[\"Fri, 05 Jun 2026 19:26:42 -0400\"],\"category\":[{\"_value\":\"HWDJY\",\"_attributes\":{\"type\":\"symbol\",\"link\":\"https://seekingalpha.com/symbol/HWDJY\"}},{\"_value\":\"HWDJF\",\"_attributes\":{\"type\":\"symbol\",\"link\":\"https://seekingalpha.com/symbol/HWDJF\"}},{\"_value\":\"SA Transcripts\",\"_attributes\":{\"type\":\"author\",\"link\":\"https://seekingalpha.com/author/sa-transcripts\"}}]},{\"title\":[\"Invinity Energy Sys Plc. 2025 Q4 - Results - Earnings Call Presentation\"],\"link\":[\"https://seekingalpha.com/article/4912534-invinity-energy-sys-plc-2025-q4-results-earnings-call-presentation?source=feed_all_articles\"],\"guid\":[{\"_value\":\"4912534\",\"_attributes\":{\"isPermaLink\":\"false\"}}],\"pubDate\":[\"Fri, 05 Jun 2026 19:26:07 -0400\"],\"category\":[{\"_value\":\"IESVF\",\"_attributes\":{\"type\":\"symbol\",\"link\":\"https://seekingalpha.com/symbol/IESVF\"}},{\"_value\":\"SA Transcripts\",\"_attributes\":{\"type\":\"author\",\"link\":\"https://seekingalpha.com/author/sa-transcripts\"}}]},{\"title\":[\"Kura Oncology, Inc. (KURA) Discusses Clinical Data and Updated Development Strategy for Darlifarnib - Slideshow\"],\"link\":[\"https://seekingalpha.com/article/4912533-kura-oncology-inc-kura-discusses-clinical-data-and-updated-development-strategy-for?source=feed_all_articles\"],\"guid\":[{\"_value\":\"4912533\",\"_attributes\":{\"isPermaLink\":\"false\"}}],\"pubDate\":[\"Fri, 05 Jun 2026 19:25:53 -0400\"],\"category\":[{\"_value\":\"KURA\",\"_attributes\":{\"type\":\"symbol\",\"link\":\"https://seekingalpha.com/symbol/KURA\"}},{\"_value\":\"SA Transcripts\",\"_attributes\":{\"type\":\"author\",\"link\":\"https://seekingalpha.com/author/sa-transcripts\"}}]},{\"title\":[\"EDAP TMS S.A. (FOCL) Analyst/Investor Day - Slideshow\"],\"link\":[\"https://seekingalpha.com/article/4912532-edap-tms-s-a-focl-analyst-investor-day-slideshow?source=feed_all_articles\"],\"guid\":[{\"_value\":\"4912532\",\"_attributes\":{\"isPermaLink\":\"false\"}}],\"pubDate\":[\"Fri, 05 Jun 2026 19:25:18 -0400\"],\"category\":[{\"_value\":\"FOCL\",\"_attributes\":{\"type\":\"symbol\",\"link\":\"https://seekingalpha.com/symbol/FOCL\"}},{\"_value\":\"SA Transcripts\",\"_attributes\":{\"type\":\"author\",\"link\":\"https://seekingalpha.com/author/sa-transcripts\"}}]},{\"title\":[\"Momentum Group Limited (MMTHF) Analyst/Investor Day - Slideshow\"],\"link\":[\"https://seekingalpha.com/article/4912531-momentum-group-limited-mmthf-analyst-investor-day-slideshow?source=feed_all_articles\"],\"guid\":[{\"_value\":\"4912531\",\"_attributes\":{\"isPermaLink\":\"false\"}}],\"pubDate\":[\"Fri, 05 Jun 2026 19:24:00 -0400\"],\"category\":[{\"_value\":\"MMTHF\",\"_attributes\":{\"type\":\"symbol\",\"link\":\"https://seekingalpha.com/symbol/MMTHF\"}},{\"_value\":\"SA Transcripts\",\"_attributes\":{\"type\":\"author\",\"link\":\"https://seekingalpha.com/author/sa-transcripts\"}}]},{\"title\":[\"Implenia AG (IPLNF) Analyst/Investor Day - Slideshow\"],\"link\":[\"https://seekingalpha.com/article/4912530-implenia-ag-iplnf-analyst-investor-day-slideshow?source=feed_all_articles\"],\"guid\":[{\"_value\":\"4912530\",\"_attributes\":{\"isPermaLink\":\"false\"}}],\"pubDate\":[\"Fri, 05 Jun 2026 19:20:06 -0400\"],\"category\":[{\"_value\":\"IPLNF\",\"_attributes\":{\"type\":\"symbol\",\"link\":\"https://seekingalpha.com/symbol/IPLNF\"}},{\"_value\":\"SA Transcripts\",\"_attributes\":{\"type\":\"author\",\"link\":\"https://seekingalpha.com/author/sa-transcripts\"}}]},{\"title\":[\"Oxford Biomedica plc (OXBDF) Analyst/Investor Day - Slideshow\"],\"link\":[\"https://seekingalpha.com/article/4912529-oxford-biomedica-plc-oxbdf-analyst-investor-day-slideshow?source=feed_all_articles\"],\"guid\":[{\"_value\":\"4912529\",\"_attributes\":{\"isPermaLink\":\"false\"}}],\"pubDate\":[\"Fri, 05 Jun 2026 19:18:12 -0400\"],\"category\":[{\"_value\":\"OXBDF\",\"_attributes\":{\"type\":\"symbol\",\"link\":\"https://seekingalpha.com/symbol/OXBDF\"}},{\"_value\":\"SA Transcripts\",\"_attributes\":{\"type\":\"author\",\"link\":\"https://seekingalpha.com/author/sa-transcripts\"}}]},{\"title\":[\"Corvus Pharmaceuticals, Inc. (CRVS) Presents at Jefferies Global Healthcare Conference 2026 - Slideshow\"],\"link\":[\"https://seekingalpha.com/article/4912528-corvus-pharmaceuticals-inc-crvs-presents-at-jefferies-global-healthcare-conference-2026?source=feed_all_articles\"],\"guid\":[{\"_value\":\"4912528\",\"_attributes\":{\"isPermaLink\":\"false\"}}],\"pubDate\":[\"Fri, 05 Jun 2026 19:16:20 -0400\"],\"category\":[{\"_value\":\"CRVS\",\"_attributes\":{\"type\":\"symbol\",\"link\":\"https://seekingalpha.com/symbol/CRVS\"}},{\"_value\":\"SA Transcripts\",\"_attributes\":{\"type\":\"author\",\"link\":\"https://seekingalpha.com/author/sa-transcripts\"}}]},{\"title\":[\"ResMed Inc. (RMD) Presents at 46th Annual William Blair Growth Stock Conference - Slideshow\"],\"link\":[\"https://seekingalpha.com/article/4912527-resmed-inc-rmd-presents-at-46th-annual-william-blair-growth-stock-conference-slideshow?source=feed_all_articles\"],\"guid\":[{\"_value\":\"4912527\",\"_attributes\":{\"isPermaLink\":\"false\"}}],\"pubDate\":[\"Fri, 05 Jun 2026 19:15:45 -0400\"],\"category\":[{\"_value\":\"RMD\",\"_attributes\":{\"type\":\"symbol\",\"link\":\"https://seekingalpha.com/symbol/RMD\"}},{\"_value\":\"RSMDF\",\"_attributes\":{\"type\":\"symbol\",\"link\":\"https://seekingalpha.com/symbol/RSMDF\"}},{\"_value\":\"SA Transcripts\",\"_attributes\":{\"type\":\"author\",\"link\":\"https://seekingalpha.com/author/sa-transcripts\"}}]},{\"title\":[\"Novanta Inc. (NOVT) Presents at Jefferies Global Healthcare Conference 2026 - Slideshow\"],\"link\":[\"https://seekingalpha.com/article/4912526-novanta-inc-novt-presents-at-jefferies-global-healthcare-conference-2026-slideshow?source=feed_all_articles\"],\"guid\":[{\"_value\":\"4912526\",\"_attributes\":{\"isPermaLink\":\"false\"}}],\"pubDate\":[\"Fri, 05 Jun 2026 19:15:00 -0400\"],\"category\":[{\"_value\":\"NOVT\",\"_attributes\":{\"type\":\"symbol\",\"link\":\"https://seekingalpha.com/symbol/NOVT\"}},{\"_value\":\"NOVTU\",\"_attributes\":{\"type\":\"symbol\",\"link\":\"https://seekingalpha.com/symbol/NOVTU\"}},{\"_value\":\"SA Transcripts\",\"_attributes\":{\"type\":\"author\",\"link\":\"https://seekingalpha.com/author/sa-transcripts\"}}]},{\"title\":[\"Guardant Health, Inc. (GH) Presents at 46th Annual William Blair Growth Stock Conference - Slideshow\"],\"link\":[\"https://seekingalpha.com/article/4912525-guardant-health-inc-gh-presents-at-46th-annual-william-blair-growth-stock-conference?source=feed_all_articles\"],\"guid\":[{\"_value\":\"4912525\",\"_attributes\":{\"isPermaLink\":\"false\"}}],\"pubDate\":[\"Fri, 05 Jun 2026 19:14:10 -0400\"],\"category\":[{\"_value\":\"GH\",\"_attributes\":{\"type\":\"symbol\",\"link\":\"https://seekingalpha.com/symbol/GH\"}},{\"_value\":\"SA Transcripts\",\"_attributes\":{\"type\":\"author\",\"link\":\"https://seekingalpha.com/author/sa-transcripts\"}}]},{\"title\":[\"Shelly Group SE (SHGPF) Shareholder/Analyst Call - Slideshow\"],\"link\":[\"https://seekingalpha.com/article/4912524-shelly-group-se-shgpf-shareholder-analyst-call-slideshow?source=feed_all_articles\"],\"guid\":[{\"_value\":\"4912524\",\"_attributes\":{\"isPermaLink\":\"false\"}}],\"pubDate\":[\"Fri, 05 Jun 2026 19:13:01 -0400\"],\"category\":[{\"_value\":\"SHGPF\",\"_attributes\":{\"type\":\"symbol\",\"link\":\"https://seekingalpha.com/symbol/SHGPF\"}},{\"_value\":\"SA Transcripts\",\"_attributes\":{\"type\":\"author\",\"link\":\"https://seekingalpha.com/author/sa-transcripts\"}}]},{\"title\":[\"Ninety One Group 2026 Q4 - Results - Earnings Call Presentation\"],\"link\":[\"https://seekingalpha.com/article/4912523-ninety-one-group-2026-q4-results-earnings-call-presentation?source=feed_all_articles\"],\"guid\":[{\"_value\":\"4912523\",\"_attributes\":{\"isPermaLink\":\"false\"}}],\"pubDate\":[\"Fri, 05 Jun 2026 19:11:25 -0400\"],\"category\":[{\"_value\":\"NINTF\",\"_attributes\":{\"type\":\"symbol\",\"link\":\"https://seekingalpha.com/symbol/NINTF\"}},{\"_value\":\"SA Transcripts\",\"_attributes\":{\"type\":\"author\",\"link\":\"https://seekingalpha.com/author/sa-transcripts\"}}]},{\"title\":[\"VersaBank 2026 Q2 - Results - Earnings Call Presentation\"],\"link\":[\"https://seekingalpha.com/article/4912522-versabank-2026-q2-results-earnings-call-presentation?source=feed_all_articles\"],\"guid\":[{\"_value\":\"4912522\",\"_attributes\":{\"isPermaLink\":\"false\"}}],\"pubDate\":[\"Fri, 05 Jun 2026 19:10:58 -0400\"],\"category\":[{\"_value\":\"VBNK:CA\",\"_attributes\":{\"type\":\"symbol\",\"link\":\"https://seekingalpha.com/symbol/VBNK:CA\"}},{\"_value\":\"VBNK\",\"_attributes\":{\"type\":\"symbol\",\"link\":\"https://seekingalpha.com/symbol/VBNK\"}},{\"_value\":\"SA Transcripts\",\"_attributes\":{\"type\":\"author\",\"link\":\"https://seekingalpha.com/author/sa-transcripts\"}}]},{\"title\":[\"Seraphim Space Investment Trust Plc 2026 Q3 - Results - Earnings Call Presentation\"],\"link\":[\"https://seekingalpha.com/article/4912521-seraphim-space-investment-trust-plc-2026-q3-results-earnings-call-presentation?source=feed_all_articles\"],\"guid\":[{\"_value\":\"4912521\",\"_attributes\":{\"isPermaLink\":\"false\"}}],\"pubDate\":[\"Fri, 05 Jun 2026 19:10:34 -0400\"],\"category\":[{\"_value\":\"SSITF\",\"_attributes\":{\"type\":\"symbol\",\"link\":\"https://seekingalpha.com/symbol/SSITF\"}},{\"_value\":\"SA Transcripts\",\"_attributes\":{\"type\":\"author\",\"link\":\"https://seekingalpha.com/author/sa-transcripts\"}}]},{\"title\":[\"Seraphim Space Investment Trust Plc 2026 Q3 - Results - Earnings Call Presentation\"],\"link\":[\"https://seekingalpha.com/article/4912520-seraphim-space-investment-trust-plc-2026-q3-results-earnings-call-presentation?source=feed_all_articles\"],\"guid\":[{\"_value\":\"4912520\",\"_attributes\":{\"isPermaLink\":\"false\"}}],\"pubDate\":[\"Fri, 05 Jun 2026 19:10:15 -0400\"],\"category\":[{\"_value\":\"SSITF\",\"_attributes\":{\"type\":\"symbol\",\"link\":\"https://seekingalpha.com/symbol/SSITF\"}},{\"_value\":\"SA Transcripts\",\"_attributes\":{\"type\":\"author\",\"link\":\"https://seekingalpha.com/author/sa-transcripts\"}}]},{\"title\":[\"Gaotu Techedu Inc. 2026 Q1 - Results - Earnings Call Presentation\"],\"link\":[\"https://seekingalpha.com/article/4912519-gaotu-techedu-inc-2026-q1-results-earnings-call-presentation?source=feed_all_articles\"],\"guid\":[{\"_value\":\"4912519\",\"_attributes\":{\"isPermaLink\":\"false\"}}],\"pubDate\":[\"Fri, 05 Jun 2026 19:09:31 -0400\"],\"category\":[{\"_value\":\"GOTU\",\"_attributes\":{\"type\":\"symbol\",\"link\":\"https://seekingalpha.com/symbol/GOTU\"}},{\"_value\":\"SA Transcripts\",\"_attributes\":{\"type\":\"author\",\"link\":\"https://seekingalpha.com/author/sa-transcripts\"}}]}]}]}} ",
  "generated": "2026-06-06T03:05:10.251Z"
}